[
  {
    "id": "10010358",
    "name": "足立　正史",
    "jobType": "事務",
    "birthDate": "1975-10-05",
    "hireDate": "2002-04-01",
    "baseSalary": 330000,
    "adjustment": 44000,
    "commute": 19700,
    "baseR8": 330000,
    "adjR8": 50000,
    "position": 60000,
    "positionR8": 60000,
    "_idx": 0,
    "_excluded": false,
    "_annualSalary": 6198000,
    "_annualSalaryR8": 6270000,
    "_upRatio": 1.1616650532429817,
    "_as": 6198000,
    "_asr": 6270000,
    "_ur": 1.1616650532429817,
    "_i": 0,
    "_ex": false,
    "_a7": 6198000,
    "_a8": 6270000,
    "_lsEx": false,
    "_blEx": false,
    "_blAge": 50,
    "_blSv": {
      "d": 8766,
      "r": 1
    },
    "_blBBase": 990000,
    "_blBConf": 1150000,
    "_blLBase": 24000,
    "_blLConf": 48000,
    "_blTotal": 1198000
  },
  {
    "id": "10010505",
    "name": "重本　由香",
    "jobType": "事務",
    "birthDate": "1984-12-29",
    "hireDate": "2007-03-15",
    "baseSalary": 175000,
    "adjustment": 35000,
    "commute": 0,
    "baseR8": 180000,
    "adjR8": 45000,
    "position": 0,
    "_idx": 2,
    "_excluded": false,
    "_annualSalary": 3045000,
    "_annualSalaryR8": 3240000,
    "_upRatio": 6.403940886699508,
    "_as": 3045000,
    "_asr": 3240000,
    "_ur": 6.403940886699508,
    "_i": 1,
    "_ex": false,
    "_a7": 3045000,
    "_a8": 3240000,
    "_lsEx": false,
    "_blEx": false,
    "_blAge": 41,
    "_blSv": {
      "d": 6957,
      "r": 1
    },
    "_blBBase": 530000,
    "_blBConf": 550000,
    "_blLBase": 65000,
    "_blLConf": 65000,
    "_blTotal": 615000
  },
  {
    "id": "10010596",
    "name": "家森　恵美子",
    "jobType": "事務",
    "birthDate": "1982-12-02",
    "hireDate": "2010-01-01",
    "baseSalary": 220000,
    "adjustment": 20000,
    "commute": 4200,
    "baseR8": 220000,
    "adjR8": 20000,
    "position": 40000,
    "positionR8": 40000,
    "_idx": 34,
    "_excluded": false,
    "_annualSalary": 4020000,
    "_annualSalaryR8": 4020000,
    "_upRatio": 0,
    "_as": 4020000,
    "_asr": 4020000,
    "_ur": 0,
    "_i": 2,
    "_ex": false,
    "_a7": 4020000,
    "_a8": 4020000,
    "_lsEx": false,
    "_blEx": false,
    "_blAge": 43,
    "_blSv": {
      "d": 5934,
      "r": 1
    },
    "_blBBase": 660000,
    "_blBConf": 700000,
    "_blLBase": 0,
    "_blLConf": 60000,
    "_blTotal": 760000
  },
  {
    "id": "10010618",
    "name": "土井　優香",
    "jobType": "事務",
    "birthDate": "1988-08-14",
    "hireDate": "2011-03-22",
    "baseSalary": 175000,
    "adjustment": 33000,
    "commute": 13500,
    "baseR8": 180000,
    "adjR8": 45000,
    "position": 0,
    "_idx": 3,
    "_excluded": false,
    "_annualSalary": 3021000,
    "_annualSalaryR8": 3240000,
    "_upRatio": 7.249255213505462,
    "_as": 3021000,
    "_asr": 3240000,
    "_ur": 7.249255213505462,
    "_i": 3,
    "_ex": false,
    "_a7": 3021000,
    "_a8": 3240000,
    "_lsEx": false,
    "_blEx": false,
    "_blAge": 37,
    "_blSv": {
      "d": 5489,
      "r": 1
    },
    "_blBBase": 530000,
    "_blBConf": 580000,
    "_blLBase": 73000,
    "_blLConf": 73000,
    "_blTotal": 653000
  },
  {
    "id": "10010641",
    "name": "横林　朋子",
    "jobType": "事務",
    "birthDate": "1978-09-19",
    "hireDate": "2012-01-01",
    "baseSalary": 175000,
    "adjustment": 34000,
    "commute": 0,
    "baseR8": 180000,
    "adjR8": 50000,
    "position": 0,
    "_idx": 4,
    "_annualSalary": 3033000,
    "_upRatio": 8.803165182987142,
    "_excluded": false,
    "_annualSalaryR8": 3300000,
    "_as": 3033000,
    "_asr": 3300000,
    "_ur": 8.803165182987142,
    "_i": 4,
    "_ex": false,
    "_a7": 3033000,
    "_a8": 3300000,
    "_lsEx": false,
    "_blEx": false,
    "_blAge": 47,
    "_blSv": {
      "d": 5204,
      "r": 1
    },
    "_blBBase": 530000,
    "_blBConf": 530000,
    "_blLBase": 89000,
    "_blLConf": 89000,
    "_blTotal": 619000
  },
  {
    "id": "10010655",
    "name": "倉田　大輔",
    "jobType": "事務",
    "birthDate": "1988-04-03",
    "hireDate": "2012-09-01",
    "baseSalary": 180000,
    "adjustment": 55000,
    "commute": 19700,
    "baseR8": 180000,
    "adjR8": 60000,
    "position": 0,
    "_idx": 5,
    "_annualSalary": 3360000,
    "_upRatio": 1.7857142857142856,
    "_excluded": false,
    "_annualSalaryR8": 3420000,
    "_as": 3360000,
    "_asr": 3420000,
    "_ur": 1.7857142857142856,
    "_i": 5,
    "_ex": false,
    "_a7": 3360000,
    "_a8": 3420000,
    "_lsEx": false,
    "_blEx": false,
    "_blAge": 37,
    "_blSv": {
      "d": 4960,
      "r": 1
    },
    "_blBBase": 540000,
    "_blBConf": 430000,
    "_blLBase": 20000,
    "_blLConf": 20000,
    "_blTotal": 450000
  },
  {
    "id": "10010728",
    "name": "太田　さなえ",
    "jobType": "事務",
    "birthDate": "1982-08-07",
    "hireDate": "2015-07-01",
    "baseSalary": 175000,
    "adjustment": 32000,
    "commute": 0,
    "baseR8": 180000,
    "adjR8": 45000,
    "position": 0,
    "_idx": 35,
    "_excluded": false,
    "_annualSalary": 3009000,
    "_annualSalaryR8": 3240000,
    "_upRatio": 7.676969092721834,
    "_as": 3009000,
    "_asr": 3240000,
    "_ur": 7.676969092721834,
    "_i": 6,
    "_ex": false,
    "_a7": 3009000,
    "_a8": 3240000,
    "_lsEx": false,
    "_blEx": false,
    "_blAge": 43,
    "_blSv": {
      "d": 3927,
      "r": 1
    },
    "_blBBase": 530000,
    "_blBConf": 550000,
    "_blLBase": 77000,
    "_blLConf": 77000,
    "_blTotal": 627000
  },
  {
    "id": "10010751",
    "name": "西道　絢加",
    "jobType": "事務",
    "birthDate": "1987-09-23",
    "hireDate": "2016-04-20",
    "baseSalary": 175000,
    "adjustment": 33000,
    "commute": 0,
    "baseR8": 180000,
    "adjR8": 45000,
    "position": 0,
    "_idx": 6,
    "_excluded": false,
    "_annualSalary": 3021000,
    "_annualSalaryR8": 3240000,
    "_upRatio": 7.249255213505462,
    "_as": 3021000,
    "_asr": 3240000,
    "_ur": 7.249255213505462,
    "_i": 7,
    "_ex": false,
    "_a7": 3021000,
    "_a8": 3240000,
    "_lsEx": false,
    "_blEx": false,
    "_blAge": 38,
    "_blSv": {
      "d": 3633,
      "r": 1
    },
    "_blBBase": 530000,
    "_blBConf": 550000,
    "_blLBase": 73000,
    "_blLConf": 73000,
    "_blTotal": 623000
  },
  {
    "id": "10020450",
    "name": "牧野　祥恵",
    "jobType": "PSW",
    "birthDate": "1983-10-20",
    "hireDate": "2004-04-01",
    "baseSalary": 224000,
    "adjustment": 40000,
    "commute": 13500,
    "baseR8": 240000,
    "adjR8": 40000,
    "position": 40000,
    "positionR8": 40000,
    "_i": 8,
    "_ex": false,
    "_a7": 4320000,
    "_a8": 4560000,
    "_ur": 5.555555555555555,
    "_lsEx": false,
    "_blEx": false,
    "_blAge": 42,
    "_blSv": {
      "d": 8035,
      "r": 1
    },
    "_blBBase": 680000,
    "_blBConf": 750000,
    "_blLBase": 80000,
    "_blLConf": 93000,
    "_blTotal": 843000
  },
  {
    "id": "10020495",
    "name": "河合　宏",
    "jobType": "PSW",
    "birthDate": "1977-10-06",
    "hireDate": "2001-04-01",
    "baseSalary": 287000,
    "adjustment": 40000,
    "commute": 13500,
    "baseR8": 300000,
    "adjR8": 40000,
    "position": 60000,
    "positionR8": 60000,
    "_idx": 8,
    "_excluded": false,
    "_annualSalary": 5505000,
    "_annualSalaryR8": 5700000,
    "_upRatio": 3.5422343324250685,
    "_as": 5505000,
    "_asr": 5700000,
    "_ur": 3.5422343324250685,
    "_i": 9,
    "_ex": false,
    "_a7": 5505000,
    "_a8": 5700000,
    "_lsEx": false,
    "_blEx": false,
    "_blAge": 48,
    "_blSv": {
      "d": 9131,
      "r": 1
    },
    "_blBBase": 870000,
    "_blBConf": 1000000,
    "_blLBase": 65000,
    "_blLConf": 100000,
    "_blTotal": 1100000
  },
  {
    "id": "10020718",
    "name": "妹尾　菜奈",
    "jobType": "PSW",
    "birthDate": "1990-09-06",
    "hireDate": "2015-04-01",
    "baseSalary": 227000,
    "adjustment": 56000,
    "commute": 13500,
    "baseR8": 230000,
    "adjR8": 60000,
    "position": 0,
    "positionR8": 0,
    "_i": 10,
    "_ex": false,
    "_a7": 4077000,
    "_a8": 4170000,
    "_ur": 2.2810890360559237,
    "_blEx": false,
    "_blAge": 35,
    "_blSv": {
      "d": 4018,
      "r": 1
    },
    "_blBBase": 690000,
    "_blBConf": 750000,
    "_blLBase": 31000,
    "_blLConf": 31000,
    "_blTotal": 781000
  },
  {
    "id": "10020767",
    "name": "嘉數　香里",
    "jobType": "PSW",
    "birthDate": "1990-12-27",
    "hireDate": "2017-03-13",
    "baseSalary": 220000,
    "adjustment": 40000,
    "commute": 19700,
    "baseR8": 220000,
    "adjR8": 60000,
    "position": 0,
    "positionR8": 0,
    "_i": 11,
    "_ex": false,
    "_a7": 3780000,
    "_a8": 4020000,
    "_ur": 6.349206349206349,
    "_blEx": false,
    "_blAge": 35,
    "_blSv": {
      "d": 3306,
      "r": 1
    },
    "_blBBase": 660000,
    "_blBConf": 660000,
    "_blLBase": 80000,
    "_blLConf": 80000,
    "_blTotal": 740000
  },
  {
    "id": "10020826",
    "name": "槇野　友香",
    "jobType": "PSW",
    "birthDate": "1996-06-04",
    "hireDate": "2019-04-01",
    "baseSalary": 196000,
    "adjustment": 40000,
    "commute": 25900,
    "baseR8": 0,
    "adjR8": 0,
    "position": 0,
    "positionR8": 0,
    "_i": 12,
    "_ex": false,
    "_a7": 3420000,
    "_a8": 0,
    "_ur": -100,
    "_lsEx": true,
    "_blEx": false,
    "_blAge": 29,
    "_blSv": {
      "d": 2557,
      "r": 1
    },
    "_blBBase": 590000,
    "_blBConf": 590000,
    "_blLBase": -1140000,
    "_blLConf": 0,
    "_blTotal": 590000
  },
  {
    "id": "10020908",
    "name": "谷澤　萌",
    "jobType": "PSW",
    "birthDate": "1998-11-23",
    "hireDate": "2021-04-01",
    "baseSalary": 196000,
    "adjustment": 40000,
    "commute": 19700,
    "baseR8": 0,
    "adjR8": 0,
    "position": 0,
    "_idx": 13,
    "_annualSalary": 3420000,
    "_upRatio": -100,
    "_excluded": false,
    "_annualSalaryR8": 0,
    "_as": 3420000,
    "_asr": 0,
    "_ur": -100,
    "_i": 13,
    "_ex": false,
    "_a7": 3420000,
    "_a8": 0,
    "_lsEx": true,
    "_blEx": false,
    "_blAge": 27,
    "_blSv": {
      "d": 1826,
      "r": 1
    },
    "_blBBase": 590000,
    "_blBConf": 590000,
    "_blLBase": -1140000,
    "_blLConf": 0,
    "_blTotal": 590000
  },
  {
    "id": "10021049",
    "name": "室　萌花",
    "jobType": "PSW",
    "birthDate": "2003-04-01",
    "hireDate": "2026-04-01",
    "baseSalary": 0,
    "adjustment": 0,
    "commute": 0,
    "baseR8": 200000,
    "adjR8": 38000,
    "position": 0,
    "positionR8": 0,
    "_i": 14,
    "_ex": false,
    "_a7": 0,
    "_a8": 3456000,
    "_ur": 0,
    "_lsEx": true,
    "_blEx": false,
    "_blAge": 22,
    "_blSv": {
      "d": 0,
      "r": 0
    },
    "_blBBase": 0,
    "_blBConf": 0,
    "_blLBase": 1152000,
    "_blLConf": 0,
    "_blTotal": 0
  },
  {
    "id": "10040186",
    "name": "池田　朋文",
    "jobType": "薬剤",
    "birthDate": "1970-03-20",
    "hireDate": "1993-04-01",
    "baseSalary": 320000,
    "adjustment": 70000,
    "commute": 19700,
    "baseR8": 320000,
    "adjR8": 80000,
    "position": 40000,
    "positionR8": 40000,
    "_idx": 14,
    "_excluded": false,
    "_annualSalary": 6120000,
    "_annualSalaryR8": 6240000,
    "_upRatio": 1.9607843137254901,
    "_as": 6120000,
    "_asr": 6240000,
    "_ur": 1.9607843137254901,
    "_i": 15,
    "_ex": false,
    "_a7": 6120000,
    "_a8": 6240000,
    "_lsEx": false,
    "_blEx": false,
    "_blAge": 56,
    "_blSv": {
      "d": 12053,
      "r": 1
    },
    "_blBBase": 960000,
    "_blBConf": 990000,
    "_blLBase": 40000,
    "_blLConf": 40000,
    "_blTotal": 1030000
  },
  {
    "id": "10060197",
    "name": "畑山　晴美",
    "jobType": "看護",
    "birthDate": "1963-09-15",
    "hireDate": "1995-05-01",
    "baseSalary": 0,
    "adjustment": 375000,
    "commute": 13500,
    "baseR8": 0,
    "adjR8": 375000,
    "position": 0,
    "positionR8": 0,
    "_i": 16,
    "_ex": false,
    "_a7": 4500000,
    "_a8": 4500000,
    "_ur": 0,
    "_blEx": false,
    "_blAge": 62,
    "_blSv": {
      "d": 11293,
      "r": 1
    },
    "_blBBase": 0,
    "_blBConf": 0,
    "_blLBase": 0,
    "_blLConf": 42000,
    "_blTotal": 42000
  },
  {
    "id": "10060446",
    "name": "坂田　翔平",
    "jobType": "看護",
    "birthDate": "1985-12-28",
    "hireDate": "2004-04-01",
    "baseSalary": 250000,
    "adjustment": 50000,
    "commute": 0,
    "baseR8": 250000,
    "adjR8": 56000,
    "position": 0,
    "positionR8": 0,
    "_i": 17,
    "_ex": false,
    "_a7": 4350000,
    "_a8": 4422000,
    "_ur": 1.6551724137931034,
    "_lsEx": false,
    "_blEx": false,
    "_blAge": 40,
    "_blSv": {
      "d": 8035,
      "r": 1
    },
    "_blBBase": 750000,
    "_blBConf": 490000,
    "_blLBase": 24000,
    "_blLConf": 30000,
    "_blTotal": 520000
  },
  {
    "id": "10060588",
    "name": "阿部　悦子",
    "jobType": "看護",
    "birthDate": "1975-08-13",
    "hireDate": "2015-03-10",
    "baseSalary": 276000,
    "adjustment": 65000,
    "commute": 13500,
    "baseR8": 280000,
    "adjR8": 65000,
    "position": 0,
    "_idx": 85,
    "_annualSalary": 4920000,
    "_upRatio": 1.2195121951219512,
    "_excluded": false,
    "_annualSalaryR8": 4980000,
    "_as": 4920000,
    "_asr": 4980000,
    "_ur": 1.2195121951219512,
    "_i": 18,
    "_ex": false,
    "_a7": 4920000,
    "_a8": 4980000,
    "_lsEx": false,
    "_blEx": false,
    "_blAge": 50,
    "_blSv": {
      "d": 4040,
      "r": 1
    },
    "_blBBase": 830000,
    "_blBConf": 880000,
    "_blLBase": 20000,
    "_blLConf": 50000,
    "_blTotal": 930000
  },
  {
    "id": "10060654",
    "name": "西　壽子",
    "jobType": "看護",
    "birthDate": "1983-03-21",
    "hireDate": "2012-09-01",
    "baseSalary": 280000,
    "adjustment": 53000,
    "commute": 0,
    "baseR8": 280000,
    "adjR8": 55000,
    "position": 40000,
    "positionR8": 40000,
    "_idx": 86,
    "_excluded": false,
    "_annualSalary": 5316000,
    "_annualSalaryR8": 5340000,
    "_upRatio": 0.4514672686230248,
    "_as": 5316000,
    "_asr": 5340000,
    "_ur": 0.4514672686230248,
    "_i": 19,
    "_ex": false,
    "_a7": 5316000,
    "_a8": 5340000,
    "_lsEx": false,
    "_blEx": false,
    "_blAge": 43,
    "_blSv": {
      "d": 4960,
      "r": 1
    },
    "_blBBase": 840000,
    "_blBConf": 950000,
    "_blLBase": 8000,
    "_blLConf": 20000,
    "_blTotal": 970000
  },
  {
    "id": "10060710",
    "name": "田中　久枝",
    "jobType": "看護",
    "birthDate": "1983-05-07",
    "hireDate": "2014-11-21",
    "baseSalary": 251000,
    "adjustment": 40000,
    "commute": 4200,
    "baseR8": 270000,
    "adjR8": 60000,
    "position": 0,
    "positionR8": 0,
    "_i": 20,
    "_ex": false,
    "_a7": 4245000,
    "_a8": 4770000,
    "_ur": 12.36749116607774,
    "_blEx": false,
    "_blAge": 42,
    "_blSv": {
      "d": 4149,
      "r": 1
    },
    "_blBBase": 760000,
    "_blBConf": 840000,
    "_blLBase": 175000,
    "_blLConf": 180000,
    "_blTotal": 1020000
  },
  {
    "id": "10060766",
    "name": "内田　ゆき",
    "jobType": "看護",
    "birthDate": "1980-07-08",
    "hireDate": "2017-03-01",
    "baseSalary": 260000,
    "adjustment": 65000,
    "commute": 4200,
    "baseR8": 260000,
    "adjR8": 55000,
    "position": 0,
    "positionR8": 40000,
    "_idx": 87,
    "_excluded": false,
    "_annualSalary": 4680000,
    "_annualSalaryR8": 5040000,
    "_upRatio": 7.6923076923076925,
    "_as": 4680000,
    "_asr": 5040000,
    "_ur": 7.6923076923076925,
    "_i": 21,
    "_ex": false,
    "_a7": 4680000,
    "_a8": 5040000,
    "_lsEx": false,
    "_blEx": false,
    "_blAge": 45,
    "_blSv": {
      "d": 3318,
      "r": 1
    },
    "_blBBase": 780000,
    "_blBConf": 880000,
    "_blLBase": 120000,
    "_blLConf": 120000,
    "_blTotal": 1000000
  },
  {
    "id": "10060768",
    "name": "児玉　規枝",
    "jobType": "看護",
    "birthDate": "1964-05-08",
    "hireDate": "2017-04-01",
    "baseSalary": 0,
    "adjustment": 400000,
    "commute": 0,
    "baseR8": 0,
    "adjR8": 375000,
    "position": 0,
    "positionR8": 0,
    "_i": 22,
    "_ex": false,
    "_a7": 4800000,
    "_a8": 4500000,
    "_ur": -6.25,
    "_blEx": false,
    "_blAge": 61,
    "_blSv": {
      "d": 3287,
      "r": 1
    },
    "_blBBase": 0,
    "_blBConf": 0,
    "_blLBase": -100000,
    "_blLConf": 0,
    "_blTotal": 0
  },
  {
    "id": "10060778",
    "name": "細川　恵里",
    "jobType": "看護",
    "birthDate": "1982-07-05",
    "hireDate": "2017-05-01",
    "baseSalary": 257000,
    "adjustment": 50000,
    "commute": 4200,
    "baseR8": 270000,
    "adjR8": 65000,
    "position": 0,
    "positionR8": 0,
    "_i": 23,
    "_ex": false,
    "_a7": 4455000,
    "_a8": 4830000,
    "_ur": 8.417508417508419,
    "_blEx": false,
    "_blAge": 43,
    "_blSv": {
      "d": 3257,
      "r": 1
    },
    "_blBBase": 780000,
    "_blBConf": 840000,
    "_blLBase": 125000,
    "_blLConf": 130000,
    "_blTotal": 970000
  },
  {
    "id": "10060851",
    "name": "上田　一樹",
    "jobType": "看護",
    "birthDate": "1994-05-03",
    "hireDate": "2024-01-22",
    "baseSalary": 240000,
    "adjustment": 50000,
    "commute": 13500,
    "baseR8": 240000,
    "adjR8": 54000,
    "position": 0,
    "positionR8": 0,
    "_i": 24,
    "_ex": false,
    "_a7": 4200000,
    "_a8": 4248000,
    "_ur": 1.1428571428571428,
    "_lsEx": false,
    "_blEx": false,
    "_blAge": 31,
    "_blSv": {
      "d": 800,
      "r": 1
    },
    "_blBBase": 720000,
    "_blBConf": 720000,
    "_blLBase": 16000,
    "_blLConf": 62000,
    "_blTotal": 782000
  },
  {
    "id": "10060854",
    "name": "島田　佳絵",
    "jobType": "看護",
    "birthDate": "1962-03-25",
    "hireDate": "2020-01-08",
    "baseSalary": 0,
    "adjustment": 410000,
    "commute": 25900,
    "baseR8": 0,
    "adjR8": 410000,
    "position": 0,
    "_idx": 91,
    "_annualSalary": 4920000,
    "_upRatio": 0,
    "_excluded": false,
    "_annualSalaryR8": 4920000,
    "_as": 4920000,
    "_asr": 4920000,
    "_ur": 0,
    "_i": 25,
    "_ex": false,
    "_a7": 4920000,
    "_a8": 4920000,
    "_lsEx": false,
    "_blEx": false,
    "_blAge": 64,
    "_blSv": {
      "d": 2275,
      "r": 1
    },
    "_blBBase": 0,
    "_blBConf": 0,
    "_blLBase": 0,
    "_blLConf": 0,
    "_blTotal": 0
  },
  {
    "id": "10060862",
    "name": "有田　美和",
    "jobType": "看護",
    "birthDate": "1970-07-12",
    "hireDate": "2020-04-01",
    "baseSalary": 256000,
    "adjustment": 75000,
    "commute": 25900,
    "baseR8": 256000,
    "adjR8": 75000,
    "position": 0,
    "positionR8": 0,
    "_i": 26,
    "_ex": false,
    "_a7": 4740000,
    "_a8": 4740000,
    "_ur": 0,
    "_lsEx": false,
    "_blEx": false,
    "_blAge": 55,
    "_blSv": {
      "d": 2191,
      "r": 1
    },
    "_blBBase": 770000,
    "_blBConf": 770000,
    "_blLBase": 0,
    "_blLConf": 0,
    "_blTotal": 770000
  },
  {
    "id": "10060863",
    "name": "森　摩李子",
    "jobType": "看護",
    "birthDate": "1991-03-24",
    "hireDate": "2024-04-01",
    "baseSalary": 243000,
    "adjustment": 40000,
    "commute": 19700,
    "baseR8": 243000,
    "adjR8": 50000,
    "position": 0,
    "positionR8": 0,
    "_i": 27,
    "_ex": false,
    "_a7": 4125000,
    "_a8": 4245000,
    "_ur": 2.909090909090909,
    "_lsEx": false,
    "_blEx": false,
    "_blAge": 35,
    "_blSv": {
      "d": 730,
      "r": 1
    },
    "_blBBase": 730000,
    "_blBConf": 730000,
    "_blLBase": 40000,
    "_blLConf": 66000,
    "_blTotal": 796000
  },
  {
    "id": "10060867",
    "name": "隠塚　恵夢",
    "jobType": "看護",
    "birthDate": "1981-06-25",
    "hireDate": "2020-03-01",
    "baseSalary": 258000,
    "adjustment": 50000,
    "commute": 19700,
    "baseR8": 270000,
    "adjR8": 65000,
    "position": 0,
    "positionR8": 0,
    "_i": 28,
    "_ex": false,
    "_a7": 4470000,
    "_a8": 4830000,
    "_ur": 8.053691275167784,
    "_blEx": false,
    "_blAge": 44,
    "_blSv": {
      "d": 2222,
      "r": 1
    },
    "_blBBase": 780000,
    "_blBConf": 800000,
    "_blLBase": 120000,
    "_blLConf": 120000,
    "_blTotal": 920000
  },
  {
    "id": "10060899",
    "name": "所谷　征省",
    "jobType": "看護",
    "birthDate": "1973-07-20",
    "hireDate": "2021-03-11",
    "baseSalary": 260000,
    "adjustment": 53000,
    "commute": 13500,
    "baseR8": 260000,
    "adjR8": 54000,
    "position": 0,
    "positionR8": 0,
    "_i": 29,
    "_ex": false,
    "_a7": 4536000,
    "_a8": 4548000,
    "_ur": 0.26455026455026454,
    "_lsEx": false,
    "_blEx": false,
    "_blAge": 52,
    "_blSv": {
      "d": 1847,
      "r": 1
    },
    "_blBBase": 780000,
    "_blBConf": 780000,
    "_blLBase": 4000,
    "_blLConf": 44000,
    "_blTotal": 824000
  },
  {
    "id": "10060903",
    "name": "太田　伸",
    "jobType": "看護",
    "birthDate": "1984-05-15",
    "hireDate": "2021-04-01",
    "baseSalary": 250000,
    "adjustment": 50000,
    "commute": 30000,
    "baseR8": 250000,
    "adjR8": 62000,
    "position": 0,
    "positionR8": 0,
    "_i": 30,
    "_ex": false,
    "_a7": 4350000,
    "_a8": 4494000,
    "_ur": 3.310344827586207,
    "_blEx": false,
    "_blAge": 41,
    "_blSv": {
      "d": 1826,
      "r": 1
    },
    "_blBBase": 750000,
    "_blBConf": 750000,
    "_blLBase": 48000,
    "_blLConf": 102000,
    "_blTotal": 852000
  },
  {
    "id": "10060933",
    "name": "國枝　航",
    "jobType": "看護",
    "birthDate": "1986-08-02",
    "hireDate": "2022-04-01",
    "baseSalary": 257000,
    "adjustment": 66000,
    "commute": 25900,
    "baseR8": 265000,
    "adjR8": 66000,
    "position": 0,
    "positionR8": 0,
    "_i": 31,
    "_ex": false,
    "_a7": 4647000,
    "_a8": 4767000,
    "_ur": 2.5823111684958038,
    "_blEx": false,
    "_blAge": 39,
    "_blSv": {
      "d": 1461,
      "r": 1
    },
    "_blBBase": 780000,
    "_blBConf": 880000,
    "_blLBase": 40000,
    "_blLConf": 90000,
    "_blTotal": 970000
  },
  {
    "id": "10060939",
    "name": "松藤　智恵美",
    "jobType": "看護",
    "birthDate": "1984-06-14",
    "hireDate": "2022-07-01",
    "baseSalary": 253000,
    "adjustment": 75000,
    "commute": 0,
    "baseR8": 253000,
    "adjR8": 75000,
    "position": 0,
    "_idx": 98,
    "_annualSalary": 4695000,
    "_upRatio": 0,
    "_excluded": false,
    "_annualSalaryR8": 4695000,
    "_as": 4695000,
    "_asr": 4695000,
    "_ur": 0,
    "_i": 32,
    "_ex": false,
    "_a7": 4695000,
    "_a8": 4695000,
    "_lsEx": false,
    "_blEx": false,
    "_blAge": 41,
    "_blSv": {
      "d": 1370,
      "r": 1
    },
    "_blBBase": 760000,
    "_blBConf": 760000,
    "_blLBase": 0,
    "_blLConf": 25000,
    "_blTotal": 785000
  },
  {
    "id": "10060948",
    "name": "細田　定子",
    "jobType": "看護",
    "birthDate": "1961-05-19",
    "hireDate": "2022-12-15",
    "baseSalary": 0,
    "adjustment": 385000,
    "commute": 0,
    "baseR8": 0,
    "adjR8": 385000,
    "position": 0,
    "positionR8": 0,
    "_i": 33,
    "_ex": false,
    "_a7": 4620000,
    "_a8": 4620000,
    "_ur": 0,
    "_lsEx": false,
    "_blEx": false,
    "_blAge": 64,
    "_blSv": {
      "d": 1203,
      "r": 1
    },
    "_blBBase": 0,
    "_blBConf": 0,
    "_blLBase": 0,
    "_blLConf": 0,
    "_blTotal": 0
  },
  {
    "id": "10060949",
    "name": "北　弘美",
    "jobType": "看護",
    "birthDate": "1983-08-12",
    "hireDate": "2023-01-01",
    "baseSalary": 251000,
    "adjustment": 40000,
    "commute": 13500,
    "baseR8": 252000,
    "adjR8": 55000,
    "position": 0,
    "_idx": 72,
    "_excluded": false,
    "_annualSalary": 4245000,
    "_annualSalaryR8": 4440000,
    "_upRatio": 4.593639575971731,
    "_as": 4245000,
    "_asr": 4440000,
    "_ur": 4.593639575971731,
    "_i": 34,
    "_ex": false,
    "_a7": 4245000,
    "_a8": 4440000,
    "_lsEx": false,
    "_blEx": false,
    "_blAge": 42,
    "_blSv": {
      "d": 1186,
      "r": 1
    },
    "_blBBase": 760000,
    "_blBConf": 630000,
    "_blLBase": 65000,
    "_blLConf": 130000,
    "_blTotal": 760000
  },
  {
    "id": "10060951",
    "name": "田中　理加",
    "jobType": "看護",
    "birthDate": "1984-01-15",
    "hireDate": "2023-01-16",
    "baseSalary": 251000,
    "adjustment": 50000,
    "commute": 13500,
    "baseR8": 252000,
    "adjR8": 55000,
    "position": 0,
    "positionR8": 0,
    "_i": 35,
    "_ex": false,
    "_a7": 4365000,
    "_a8": 4440000,
    "_ur": 1.718213058419244,
    "_lsEx": false,
    "_blEx": false,
    "_blAge": 42,
    "_blSv": {
      "d": 1171,
      "r": 1
    },
    "_blBBase": 760000,
    "_blBConf": 760000,
    "_blLBase": 25000,
    "_blLConf": 93000,
    "_blTotal": 853000
  },
  {
    "id": "10060952",
    "name": "赤井　一之",
    "jobType": "看護",
    "birthDate": "1984-11-22",
    "hireDate": "2023-02-01",
    "baseSalary": 260000,
    "adjustment": 79000,
    "commute": 19700,
    "baseR8": 260000,
    "adjR8": 55000,
    "position": 0,
    "positionR8": 40000,
    "_i": 36,
    "_ex": false,
    "_a7": 4848000,
    "_a8": 5040000,
    "_ur": 3.9603960396039604,
    "_lsEx": false,
    "_blEx": false,
    "_blAge": 41,
    "_blSv": {
      "d": 1155,
      "r": 1
    },
    "_blBBase": 780000,
    "_blBConf": 880000,
    "_blLBase": 64000,
    "_blLConf": 130000,
    "_blTotal": 1010000
  },
  {
    "id": "10060955",
    "name": "池田　麻美",
    "jobType": "看護",
    "birthDate": "1988-07-05",
    "hireDate": "2023-04-01",
    "baseSalary": 246000,
    "adjustment": 50000,
    "commute": 19700,
    "baseR8": 250000,
    "adjR8": 58000,
    "position": 0,
    "positionR8": 0,
    "_i": 37,
    "_ex": false,
    "_a7": 4290000,
    "_a8": 4446000,
    "_ur": 3.6363636363636362,
    "_blEx": false,
    "_blAge": 37,
    "_blSv": {
      "d": 1096,
      "r": 1
    },
    "_blBBase": 740000,
    "_blBConf": 460000,
    "_blLBase": 52000,
    "_blLConf": 110000,
    "_blTotal": 570000
  },
  {
    "id": "10060956",
    "name": "井村　純",
    "jobType": "看護",
    "birthDate": "1972-10-12",
    "hireDate": "2023-04-01",
    "baseSalary": 400000,
    "adjustment": 50000,
    "commute": 10030,
    "baseR8": 400000,
    "adjR8": 55000,
    "position": 60000,
    "positionR8": 60000,
    "_idx": 102,
    "_excluded": false,
    "_annualSalary": 7320000,
    "_annualSalaryR8": 7380000,
    "_upRatio": 0.819672131147541,
    "_as": 7320000,
    "_asr": 7380000,
    "_ur": 0.819672131147541,
    "_i": 38,
    "_ex": false,
    "_a7": 7320000,
    "_a8": 7380000,
    "_lsEx": false,
    "_blEx": false,
    "_blAge": 53,
    "_blSv": {
      "d": 1096,
      "r": 1
    },
    "_blBBase": 1200000,
    "_blBConf": 1300000,
    "_blLBase": 20000,
    "_blLConf": 70000,
    "_blTotal": 1370000
  },
  {
    "id": "10060958",
    "name": "平松　深雪",
    "jobType": "看護",
    "birthDate": "1983-10-01",
    "hireDate": "2023-05-08",
    "baseSalary": 260000,
    "adjustment": 67000,
    "commute": 4200,
    "baseR8": 260000,
    "adjR8": 55000,
    "position": 0,
    "positionR8": 40000,
    "_idx": 103,
    "_excluded": false,
    "_annualSalary": 4704000,
    "_annualSalaryR8": 5040000,
    "_upRatio": 7.142857142857142,
    "_as": 4704000,
    "_asr": 5040000,
    "_ur": 7.142857142857142,
    "_i": 39,
    "_ex": false,
    "_a7": 4704000,
    "_a8": 5040000,
    "_lsEx": false,
    "_blEx": false,
    "_blAge": 42,
    "_blSv": {
      "d": 1059,
      "r": 1
    },
    "_blBBase": 780000,
    "_blBConf": 0,
    "_blLBase": 112000,
    "_blLConf": 150000,
    "_blTotal": 150000
  },
  {
    "id": "10060959",
    "name": "芥川　今日子",
    "jobType": "看護",
    "birthDate": "1986-07-29",
    "hireDate": "2023-05-08",
    "baseSalary": 253000,
    "adjustment": 50000,
    "commute": 13500,
    "baseR8": 260000,
    "adjR8": 60000,
    "position": 0,
    "positionR8": 0,
    "_i": 40,
    "_ex": false,
    "_a7": 4395000,
    "_a8": 4620000,
    "_ur": 5.1194539249146755,
    "_blEx": false,
    "_blAge": 39,
    "_blSv": {
      "d": 1059,
      "r": 1
    },
    "_blBBase": 760000,
    "_blBConf": 800000,
    "_blLBase": 75000,
    "_blLConf": 80000,
    "_blTotal": 880000
  },
  {
    "id": "10060984",
    "name": "堀　あゆみ",
    "jobType": "看護",
    "birthDate": "1975-09-26",
    "hireDate": "2024-02-26",
    "baseSalary": 259000,
    "adjustment": 50000,
    "commute": 19700,
    "baseR8": 260000,
    "adjR8": 54000,
    "position": 0,
    "positionR8": 0,
    "_i": 41,
    "_ex": false,
    "_a7": 4485000,
    "_a8": 4548000,
    "_ur": 1.4046822742474918,
    "_lsEx": false,
    "_blEx": false,
    "_blAge": 50,
    "_blSv": {
      "d": 765,
      "r": 1
    },
    "_blBBase": 780000,
    "_blBConf": 780000,
    "_blLBase": 21000,
    "_blLConf": 57000,
    "_blTotal": 837000
  },
  {
    "id": "10060985",
    "name": "西川　敬太郎",
    "jobType": "看護",
    "birthDate": "1997-06-26",
    "hireDate": "2024-03-01",
    "baseSalary": 231000,
    "adjustment": 54000,
    "commute": 19700,
    "baseR8": 240000,
    "adjR8": 66000,
    "position": 0,
    "positionR8": 0,
    "_i": 42,
    "_ex": false,
    "_a7": 4113000,
    "_a8": 4392000,
    "_ur": 6.783369803063458,
    "_blEx": false,
    "_blAge": 28,
    "_blSv": {
      "d": 761,
      "r": 1
    },
    "_blBBase": 700000,
    "_blBConf": 750000,
    "_blLBase": 93000,
    "_blLConf": 140000,
    "_blTotal": 890000
  },
  {
    "id": "10060986",
    "name": "古林　千加",
    "jobType": "看護",
    "birthDate": "1963-05-18",
    "hireDate": "2024-03-21",
    "baseSalary": 0,
    "adjustment": 375000,
    "commute": 13500,
    "baseR8": 0,
    "adjR8": 380000,
    "position": 0,
    "positionR8": 0,
    "_i": 43,
    "_ex": false,
    "_a7": 4500000,
    "_a8": 4560000,
    "_ur": 1.3333333333333335,
    "_lsEx": false,
    "_blEx": false,
    "_blAge": 62,
    "_blSv": {
      "d": 741,
      "r": 1
    },
    "_blBBase": 0,
    "_blBConf": 0,
    "_blLBase": 20000,
    "_blLConf": 80000,
    "_blTotal": 80000
  },
  {
    "id": "10060987",
    "name": "小川　修一",
    "jobType": "看護",
    "birthDate": "1974-04-25",
    "hireDate": "2024-04-01",
    "baseSalary": 260000,
    "adjustment": 50000,
    "commute": 0,
    "baseR8": 260000,
    "adjR8": 50000,
    "position": 0,
    "positionR8": 0,
    "_i": 44,
    "_ex": false,
    "_a7": 4500000,
    "_a8": 4500000,
    "_ur": 0,
    "_blEx": false,
    "_blAge": 51,
    "_blSv": {
      "d": 730,
      "r": 1
    },
    "_blBBase": 780000,
    "_blBConf": 780000,
    "_blLBase": 0,
    "_blLConf": 60000,
    "_blTotal": 840000
  },
  {
    "id": "10060990",
    "name": "中原　大輔",
    "jobType": "看護",
    "birthDate": "1981-08-17",
    "hireDate": "2024-04-21",
    "baseSalary": 253000,
    "adjustment": 50000,
    "commute": 4200,
    "baseR8": 254000,
    "adjR8": 55000,
    "position": 0,
    "positionR8": 0,
    "_i": 45,
    "_ex": false,
    "_a7": 4395000,
    "_a8": 4470000,
    "_ur": 1.7064846416382253,
    "_blEx": false,
    "_blAge": 44,
    "_blSv": {
      "d": 710,
      "r": 1
    },
    "_blBBase": 760000,
    "_blBConf": 760000,
    "_blLBase": 25000,
    "_blLConf": 86000,
    "_blTotal": 846000
  },
  {
    "id": "10060993",
    "name": "橋本　昌樹",
    "jobType": "看護",
    "birthDate": "1993-08-13",
    "hireDate": "2024-05-07",
    "baseSalary": 241000,
    "adjustment": 60000,
    "commute": 19700,
    "baseR8": 242000,
    "adjR8": 60000,
    "position": 0,
    "_idx": 110,
    "_annualSalary": 4335000,
    "_upRatio": 0.34602076124567477,
    "_excluded": false,
    "_annualSalaryR8": 4350000,
    "_as": 4335000,
    "_asr": 4350000,
    "_ur": 0.34602076124567477,
    "_i": 46,
    "_ex": false,
    "_a7": 4335000,
    "_a8": 4350000,
    "_lsEx": false,
    "_blEx": false,
    "_blAge": 32,
    "_blSv": {
      "d": 694,
      "r": 1
    },
    "_blBBase": 730000,
    "_blBConf": 750000,
    "_blLBase": 5000,
    "_blLConf": 33000,
    "_blTotal": 783000
  },
  {
    "id": "10061002",
    "name": "山口　小百合",
    "jobType": "看護",
    "birthDate": "1998-03-07",
    "hireDate": "2024-07-21",
    "baseSalary": 231000,
    "adjustment": 50000,
    "commute": 25900,
    "baseR8": 240000,
    "adjR8": 63000,
    "position": 0,
    "positionR8": 0,
    "_i": 47,
    "_ex": false,
    "_a7": 4065000,
    "_a8": 4356000,
    "_ur": 7.158671586715867,
    "_blEx": false,
    "_blAge": 28,
    "_blSv": {
      "d": 619,
      "r": 1
    },
    "_blBBase": 700000,
    "_blBConf": 700000,
    "_blLBase": 97000,
    "_blLConf": 145000,
    "_blTotal": 845000
  },
  {
    "id": "10061003",
    "name": "難波　良彰",
    "jobType": "看護",
    "birthDate": "1999-05-25",
    "hireDate": "2024-09-01",
    "baseSalary": 225000,
    "adjustment": 50000,
    "commute": 13500,
    "baseR8": 240000,
    "adjR8": 50000,
    "position": 0,
    "_idx": 80,
    "_excluded": false,
    "_annualSalary": 3975000,
    "_annualSalaryR8": 4200000,
    "_upRatio": 5.660377358490567,
    "_as": 3975000,
    "_asr": 4200000,
    "_ur": 5.660377358490567,
    "_i": 48,
    "_ex": false,
    "_a7": 3975000,
    "_a8": 4200000,
    "_lsEx": false,
    "_blEx": false,
    "_blAge": 26,
    "_blSv": {
      "d": 577,
      "r": 1
    },
    "_blBBase": 680000,
    "_blBConf": 680000,
    "_blLBase": 75000,
    "_blLConf": 127000,
    "_blTotal": 807000
  },
  {
    "id": "10061007",
    "name": "平松　英恵",
    "jobType": "看護",
    "birthDate": "1999-10-05",
    "hireDate": "2024-09-02",
    "baseSalary": 225000,
    "adjustment": 50000,
    "commute": 13500,
    "baseR8": 240000,
    "adjR8": 52000,
    "position": 0,
    "positionR8": 0,
    "_i": 49,
    "_ex": false,
    "_a7": 3975000,
    "_a8": 4224000,
    "_ur": 6.264150943396227,
    "_lsEx": false,
    "_blEx": false,
    "_blAge": 26,
    "_blSv": {
      "d": 576,
      "r": 1
    },
    "_blBBase": 680000,
    "_blBConf": 680000,
    "_blLBase": 83000,
    "_blLConf": 120000,
    "_blTotal": 800000
  },
  {
    "id": "10061018",
    "name": "久保　彩夏",
    "jobType": "看護",
    "birthDate": "2000-08-17",
    "hireDate": "2025-03-01",
    "baseSalary": 222000,
    "adjustment": 50000,
    "commute": 13500,
    "baseR8": 240000,
    "adjR8": 58000,
    "position": 0,
    "positionR8": 0,
    "_i": 50,
    "_ex": false,
    "_a7": 3930000,
    "_a8": 4296000,
    "_ur": 9.31297709923664,
    "_blEx": false,
    "_blAge": 25,
    "_blSv": {
      "d": 396,
      "r": 1
    },
    "_blBBase": 670000,
    "_blBConf": 670000,
    "_blLBase": 122000,
    "_blLConf": 190000,
    "_blTotal": 860000
  },
  {
    "id": "10061038",
    "name": "吉村　一良",
    "jobType": "看護",
    "birthDate": "1975-03-06",
    "hireDate": "2025-06-23",
    "baseSalary": 260000,
    "adjustment": 50000,
    "commute": 25900,
    "baseR8": 260000,
    "adjR8": 50000,
    "position": 0,
    "positionR8": 0,
    "_i": 51,
    "_ex": false,
    "_a7": 4500000,
    "_a8": 4500000,
    "_ur": 0,
    "_lsEx": false,
    "_blEx": false,
    "_blAge": 51,
    "_blSv": {
      "d": 282,
      "r": 0.7726027397260274
    },
    "_blBBase": 610000,
    "_blBConf": 610000,
    "_blLBase": 0,
    "_blLConf": 21000,
    "_blTotal": 631000
  },
  {
    "id": "10061042",
    "name": "末森　愛子",
    "jobType": "看護",
    "birthDate": "1973-12-27",
    "hireDate": "2025-10-16",
    "baseSalary": 260000,
    "adjustment": 50000,
    "commute": 19700,
    "baseR8": 260000,
    "adjR8": 52000,
    "position": 0,
    "positionR8": 0,
    "_i": 52,
    "_ex": false,
    "_a7": 4500000,
    "_a8": 4524000,
    "_ur": 0.5333333333333333,
    "_blEx": false,
    "_blAge": 52,
    "_blSv": {
      "d": 167,
      "r": 0.4575342465753425
    },
    "_blBBase": 360000,
    "_blBConf": 360000,
    "_blLBase": 8000,
    "_blLConf": 24000,
    "_blTotal": 384000
  },
  {
    "id": "10061045",
    "name": "柴田　亮",
    "jobType": "看護",
    "birthDate": "1995-06-30",
    "hireDate": "2026-03-01",
    "baseSalary": 240000,
    "adjustment": 50000,
    "commute": 0,
    "baseR8": 240000,
    "adjR8": 50000,
    "position": 0,
    "positionR8": 0,
    "_i": 53,
    "_ex": false,
    "_a7": 4200000,
    "_a8": 4200000,
    "_ur": 0,
    "_lsEx": false,
    "_blEx": false,
    "_blAge": 30,
    "_blSv": {
      "d": 31,
      "r": 0.08493150684931507
    },
    "_blBBase": 70000,
    "_blBConf": 0,
    "_blLBase": 0,
    "_blLConf": 0,
    "_blTotal": 0
  },
  {
    "id": "10061052",
    "name": "石井　邦男",
    "jobType": "看護",
    "birthDate": "1989-03-03",
    "hireDate": "2026-03-01",
    "baseSalary": 246000,
    "adjustment": 50000,
    "commute": 0,
    "baseR8": 246000,
    "adjR8": 50000,
    "position": 0,
    "positionR8": 0,
    "_i": 54,
    "_ex": false,
    "_a7": 4290000,
    "_a8": 4290000,
    "_ur": 0,
    "_lsEx": false,
    "_blEx": false,
    "_blAge": 37,
    "_blSv": {
      "d": 31,
      "r": 0.08493150684931507
    },
    "_blBBase": 70000,
    "_blBConf": 0,
    "_blLBase": 0,
    "_blLConf": 0,
    "_blTotal": 0
  },
  {
    "id": "10061056",
    "name": "塩尻　雅子",
    "jobType": "看護",
    "birthDate": "1989-03-02",
    "hireDate": "2026-03-01",
    "baseSalary": 246000,
    "adjustment": 50000,
    "commute": 19700,
    "baseR8": 246000,
    "adjR8": 50000,
    "position": 0,
    "positionR8": 0,
    "_i": 55,
    "_ex": false,
    "_a7": 4290000,
    "_a8": 4290000,
    "_ur": 0,
    "_lsEx": false,
    "_blEx": false,
    "_blAge": 37,
    "_blSv": {
      "d": 31,
      "r": 0.08493150684931507
    },
    "_blBBase": 70000,
    "_blBConf": 0,
    "_blLBase": 0,
    "_blLConf": 0,
    "_blTotal": 0
  },
  {
    "id": "10061059",
    "name": "横道　瑛子",
    "jobType": "看護",
    "birthDate": "1984-10-16",
    "hireDate": "2026-04-01",
    "baseSalary": 0,
    "adjustment": 0,
    "commute": 0,
    "baseR8": 250000,
    "adjR8": 50000,
    "position": 0,
    "positionR8": 0,
    "_i": 56,
    "_ex": false,
    "_a7": 0,
    "_a8": 4350000,
    "_ur": 0,
    "_lsEx": false,
    "_blEx": false,
    "_blAge": 41,
    "_blSv": {
      "d": 0,
      "r": 0
    },
    "_blBBase": 0,
    "_blBConf": 0,
    "_blLBase": 1450000,
    "_blLConf": 0,
    "_blTotal": 0
  },
  {
    "id": "10061060",
    "name": "守屋　稔久",
    "jobType": "看護",
    "birthDate": "1980-01-18",
    "hireDate": "2026-03-01",
    "baseSalary": 250000,
    "adjustment": 50000,
    "commute": 19700,
    "baseR8": 250000,
    "adjR8": 50000,
    "position": 0,
    "positionR8": 0,
    "_i": 57,
    "_ex": false,
    "_a7": 4350000,
    "_a8": 4350000,
    "_ur": 0,
    "_lsEx": false,
    "_blEx": false,
    "_blAge": 46,
    "_blSv": {
      "d": 31,
      "r": 0.08493150684931507
    },
    "_blBBase": 70000,
    "_blBConf": 0,
    "_blLBase": 0,
    "_blLConf": 0,
    "_blTotal": 0
  },
  {
    "id": "10070285",
    "name": "信下　弘子",
    "jobType": "准看",
    "birthDate": "1963-08-25",
    "hireDate": "1998-03-01",
    "baseSalary": 0,
    "adjustment": 325000,
    "commute": 7300,
    "baseR8": 0,
    "adjR8": 330000,
    "position": 0,
    "_idx": 15,
    "_annualSalary": 3900000,
    "_upRatio": 1.5384615384615385,
    "_excluded": false,
    "_annualSalaryR8": 3960000,
    "_as": 3900000,
    "_asr": 3960000,
    "_ur": 1.5384615384615385,
    "_i": 58,
    "_ex": false,
    "_a7": 3900000,
    "_a8": 3960000,
    "_lsEx": false,
    "_blEx": false,
    "_blAge": 62,
    "_blSv": {
      "d": 10258,
      "r": 1
    },
    "_blBBase": 0,
    "_blBConf": 0,
    "_blLBase": 20000,
    "_blLConf": 50000,
    "_blTotal": 50000
  },
  {
    "id": "10070493",
    "name": "住田　里美",
    "jobType": "准看",
    "birthDate": "1961-08-21",
    "hireDate": "2006-08-07",
    "baseSalary": 0,
    "adjustment": 0,
    "commute": 0,
    "baseR8": 0,
    "adjR8": 0,
    "position": 0,
    "positionR8": 0,
    "_i": 59,
    "_ex": false,
    "_a7": 0,
    "_a8": 0,
    "_ur": 0,
    "_lsEx": true,
    "_blEx": false,
    "_blAge": 64,
    "_blSv": {
      "d": 7177,
      "r": 1
    },
    "_blBBase": 0,
    "_blBConf": 0,
    "_blLBase": 0,
    "_blLConf": 0,
    "_blTotal": 0
  },
  {
    "id": "10070693",
    "name": "林　大輔",
    "jobType": "准看",
    "birthDate": "1992-08-27",
    "hireDate": "2021-03-08",
    "baseSalary": 189000,
    "adjustment": 45000,
    "commute": 0,
    "baseR8": 190000,
    "adjR8": 50000,
    "position": 0,
    "_idx": 17,
    "_excluded": false,
    "_annualSalary": 3375000,
    "_annualSalaryR8": 3450000,
    "_upRatio": 2.2222222222222223,
    "_as": 3375000,
    "_asr": 3450000,
    "_ur": 2.2222222222222223,
    "_i": 60,
    "_ex": false,
    "_a7": 3375000,
    "_a8": 3450000,
    "_lsEx": false,
    "_blEx": false,
    "_blAge": 33,
    "_blSv": {
      "d": 1850,
      "r": 1
    },
    "_blBBase": 570000,
    "_blBConf": 570000,
    "_blLBase": 25000,
    "_blLConf": 86000,
    "_blTotal": 656000
  },
  {
    "id": "10070883",
    "name": "大倉　三鈴",
    "jobType": "准看",
    "birthDate": "1961-03-22",
    "hireDate": "2020-09-01",
    "baseSalary": 227000,
    "adjustment": 45000,
    "commute": 25900,
    "baseR8": 0,
    "adjR8": 0,
    "position": 0,
    "_idx": 19,
    "_annualSalary": 3945000,
    "_upRatio": -100,
    "_excluded": false,
    "_annualSalaryR8": 0,
    "_as": 3945000,
    "_asr": 0,
    "_ur": -100,
    "_i": 61,
    "_ex": false,
    "_a7": 3945000,
    "_a8": 0,
    "_lsEx": true,
    "_blEx": false,
    "_blAge": 65,
    "_blSv": {
      "d": 2038,
      "r": 1
    },
    "_blBBase": 690000,
    "_blBConf": 690000,
    "_blLBase": -1315000,
    "_blLConf": 0,
    "_blTotal": 690000
  },
  {
    "id": "10070972",
    "name": "阿部　忍",
    "jobType": "准看",
    "birthDate": "1977-01-10",
    "hireDate": "2024-01-08",
    "baseSalary": 220000,
    "adjustment": 45000,
    "commute": 4200,
    "baseR8": 220000,
    "adjR8": 50000,
    "position": 0,
    "_idx": 79,
    "_excluded": false,
    "_annualSalary": 3840000,
    "_annualSalaryR8": 3900000,
    "_upRatio": 1.5625,
    "_as": 3840000,
    "_asr": 3900000,
    "_ur": 1.5625,
    "_i": 62,
    "_ex": false,
    "_a7": 3840000,
    "_a8": 3900000,
    "_lsEx": false,
    "_blEx": false,
    "_blAge": 49,
    "_blSv": {
      "d": 814,
      "r": 1
    },
    "_blBBase": 660000,
    "_blBConf": 600000,
    "_blLBase": 20000,
    "_blLConf": 39000,
    "_blTotal": 639000
  },
  {
    "id": "10071043",
    "name": "岩佐　崇生",
    "jobType": "准看",
    "birthDate": "1972-10-13",
    "hireDate": "2025-09-08",
    "baseSalary": 220000,
    "adjustment": 45000,
    "commute": 13500,
    "baseR8": 220000,
    "adjR8": 50000,
    "position": 0,
    "_idx": 115,
    "_excluded": false,
    "_annualSalary": 3840000,
    "_annualSalaryR8": 3900000,
    "_upRatio": 1.5625,
    "_as": 3840000,
    "_asr": 3900000,
    "_ur": 1.5625,
    "_i": 63,
    "_ex": false,
    "_a7": 3840000,
    "_a8": 3900000,
    "_lsEx": false,
    "_blEx": false,
    "_blAge": 53,
    "_blSv": {
      "d": 205,
      "r": 0.5616438356164384
    },
    "_blBBase": 380000,
    "_blBConf": 380000,
    "_blLBase": 20000,
    "_blLConf": 76000,
    "_blTotal": 456000
  },
  {
    "id": "10080239",
    "name": "藤村　貴子",
    "jobType": "補助",
    "birthDate": "1973-09-05",
    "hireDate": "1995-09-01",
    "baseSalary": 191000,
    "adjustment": 39000,
    "commute": 7300,
    "baseR8": 192000,
    "adjR8": 40000,
    "position": 0,
    "positionR8": 0,
    "_i": 64,
    "_ex": false,
    "_a7": 3333000,
    "_a8": 3360000,
    "_ur": 0.8100810081008101,
    "_blEx": false,
    "_blAge": 52,
    "_blSv": {
      "d": 11170,
      "r": 1
    },
    "_blBBase": 580000,
    "_blBConf": 580000,
    "_blLBase": 9000,
    "_blLConf": 9000,
    "_blTotal": 589000
  },
  {
    "id": "10080365",
    "name": "川原　比呂子",
    "jobType": "補助",
    "birthDate": "1966-11-26",
    "hireDate": "2002-04-01",
    "baseSalary": 162000,
    "adjustment": 38000,
    "commute": 13500,
    "baseR8": 160000,
    "adjR8": 42000,
    "position": 0,
    "positionR8": 0,
    "_i": 65,
    "_ex": false,
    "_a7": 2886000,
    "_a8": 2904000,
    "_ur": 0.6237006237006237,
    "_lsEx": false,
    "_blEx": false,
    "_blAge": 59,
    "_blSv": {
      "d": 8766,
      "r": 1
    },
    "_blBBase": 490000,
    "_blBConf": 490000,
    "_blLBase": 6000,
    "_blLConf": 27000,
    "_blTotal": 517000
  },
  {
    "id": "10080424",
    "name": "佐藤　ユリ子",
    "jobType": "補助",
    "birthDate": "1962-12-03",
    "hireDate": "2003-05-06",
    "baseSalary": 0,
    "adjustment": 213000,
    "commute": 13500,
    "baseR8": 0,
    "adjR8": 213000,
    "position": 0,
    "positionR8": 0,
    "_i": 66,
    "_ex": false,
    "_a7": 2556000,
    "_a8": 2556000,
    "_ur": 0,
    "_blEx": false,
    "_blAge": 63,
    "_blSv": {
      "d": 8366,
      "r": 1
    },
    "_blBBase": 0,
    "_blBConf": 0,
    "_blLBase": 0,
    "_blLConf": 0,
    "_blTotal": 0
  },
  {
    "id": "10080431",
    "name": "森谷　民子",
    "jobType": "補助",
    "birthDate": "1961-08-13",
    "hireDate": "2003-09-01",
    "baseSalary": 0,
    "adjustment": 213000,
    "commute": 13500,
    "baseR8": 0,
    "adjR8": 213000,
    "position": 0,
    "positionR8": 0,
    "_i": 67,
    "_ex": false,
    "_a7": 2556000,
    "_a8": 2556000,
    "_ur": 0,
    "_blEx": false,
    "_blAge": 64,
    "_blSv": {
      "d": 8248,
      "r": 1
    },
    "_blBBase": 0,
    "_blBConf": 0,
    "_blLBase": 0,
    "_blLConf": 0,
    "_blTotal": 0
  },
  {
    "id": "10080483",
    "name": "崎岡　恵子",
    "jobType": "補助",
    "birthDate": "1962-03-27",
    "hireDate": "2006-05-01",
    "baseSalary": 0,
    "adjustment": 213000,
    "commute": 4200,
    "baseR8": 0,
    "adjR8": 228000,
    "position": 0,
    "positionR8": 0,
    "_i": 68,
    "_ex": false,
    "_a7": 2556000,
    "_a8": 2736000,
    "_ur": 7.042253521126761,
    "_blEx": false,
    "_blAge": 64,
    "_blSv": {
      "d": 7275,
      "r": 1
    },
    "_blBBase": 0,
    "_blBConf": 0,
    "_blLBase": 60000,
    "_blLConf": 79000,
    "_blTotal": 79000
  },
  {
    "id": "10080496",
    "name": "小林　ケイ子",
    "jobType": "補助",
    "birthDate": "1966-10-20",
    "hireDate": "2006-10-01",
    "baseSalary": 145000,
    "adjustment": 38000,
    "commute": 13500,
    "baseR8": 145000,
    "adjR8": 38000,
    "position": 0,
    "_idx": 25,
    "_annualSalary": 2631000,
    "_upRatio": 0,
    "_excluded": false,
    "_annualSalaryR8": 2631000,
    "_as": 2631000,
    "_asr": 2631000,
    "_ur": 0,
    "_i": 69,
    "_ex": false,
    "_a7": 2631000,
    "_a8": 2631000,
    "_lsEx": false,
    "_blEx": false,
    "_blAge": 59,
    "_blSv": {
      "d": 7122,
      "r": 1
    },
    "_blBBase": 440000,
    "_blBConf": 440000,
    "_blLBase": 0,
    "_blLConf": 0,
    "_blTotal": 440000
  },
  {
    "id": "10080543",
    "name": "冨弥　艶子",
    "jobType": "補助",
    "birthDate": "1964-03-25",
    "hireDate": "2008-08-07",
    "baseSalary": 0,
    "adjustment": 213000,
    "commute": 0,
    "baseR8": 0,
    "adjR8": 213000,
    "position": 0,
    "positionR8": 0,
    "_i": 70,
    "_ex": false,
    "_a7": 2556000,
    "_a8": 2556000,
    "_ur": 0,
    "_blEx": false,
    "_blAge": 62,
    "_blSv": {
      "d": 6446,
      "r": 1
    },
    "_blBBase": 0,
    "_blBConf": 0,
    "_blLBase": 0,
    "_blLConf": 0,
    "_blTotal": 0
  },
  {
    "id": "10080561",
    "name": "岡崎　貞夫",
    "jobType": "補助",
    "birthDate": "1971-01-10",
    "hireDate": "2009-02-09",
    "baseSalary": 184000,
    "adjustment": 30000,
    "commute": 19700,
    "baseR8": 200000,
    "adjR8": 50000,
    "position": 0,
    "positionR8": 0,
    "_i": 71,
    "_ex": false,
    "_a7": 3120000,
    "_a8": 3600000,
    "_ur": 15.384615384615385,
    "_blEx": false,
    "_blAge": 55,
    "_blSv": {
      "d": 6260,
      "r": 1
    },
    "_blBBase": 560000,
    "_blBConf": 560000,
    "_blLBase": 160000,
    "_blLConf": 189000,
    "_blTotal": 749000
  },
  {
    "id": "10080617",
    "name": "前野　晶子",
    "jobType": "補助",
    "birthDate": "1974-04-29",
    "hireDate": "2011-03-01",
    "baseSalary": 160000,
    "adjustment": 38000,
    "commute": 4200,
    "baseR8": 180000,
    "adjR8": 55000,
    "position": 0,
    "positionR8": 0,
    "_i": 72,
    "_ex": false,
    "_a7": 2856000,
    "_a8": 3360000,
    "_ur": 17.647058823529413,
    "_blEx": false,
    "_blAge": 51,
    "_blSv": {
      "d": 5510,
      "r": 1
    },
    "_blBBase": 480000,
    "_blBConf": 480000,
    "_blLBase": 168000,
    "_blLConf": 195000,
    "_blTotal": 675000
  },
  {
    "id": "10080648",
    "name": "石井　泉",
    "jobType": "補助",
    "birthDate": "1965-06-29",
    "hireDate": "2012-05-01",
    "baseSalary": 0,
    "adjustment": 226000,
    "commute": 0,
    "baseR8": 0,
    "adjR8": 228000,
    "position": 0,
    "positionR8": 0,
    "_i": 73,
    "_ex": false,
    "_a7": 2712000,
    "_a8": 2736000,
    "_ur": 0.8849557522123894,
    "_blEx": false,
    "_blAge": 60,
    "_blSv": {
      "d": 5083,
      "r": 1
    },
    "_blBBase": 0,
    "_blBConf": 0,
    "_blLBase": 8000,
    "_blLConf": 35000,
    "_blTotal": 35000
  },
  {
    "id": "10080680",
    "name": "畑山　洋一",
    "jobType": "補助",
    "birthDate": "1987-01-21",
    "hireDate": "2013-06-01",
    "baseSalary": 178000,
    "adjustment": 35000,
    "commute": 13500,
    "baseR8": 200000,
    "adjR8": 60000,
    "position": 0,
    "positionR8": 0,
    "_i": 74,
    "_ex": false,
    "_a7": 3090000,
    "_a8": 3720000,
    "_ur": 20.388349514563107,
    "_lsEx": false,
    "_blEx": false,
    "_blAge": 39,
    "_blSv": {
      "d": 4687,
      "r": 1
    },
    "_blBBase": 540000,
    "_blBConf": 540000,
    "_blLBase": 210000,
    "_blLConf": 280000,
    "_blTotal": 820000
  },
  {
    "id": "10080689",
    "name": "樋口　裕正",
    "jobType": "補助",
    "birthDate": "1983-10-13",
    "hireDate": "2014-03-01",
    "baseSalary": 160000,
    "adjustment": 38000,
    "commute": 0,
    "baseR8": 160000,
    "adjR8": 42000,
    "position": 0,
    "positionR8": 0,
    "_i": 75,
    "_ex": false,
    "_a7": 2856000,
    "_a8": 2904000,
    "_ur": 1.680672268907563,
    "_lsEx": false,
    "_blEx": false,
    "_blAge": 42,
    "_blSv": {
      "d": 4414,
      "r": 1
    },
    "_blBBase": 480000,
    "_blBConf": 480000,
    "_blLBase": 16000,
    "_blLConf": 36000,
    "_blTotal": 516000
  },
  {
    "id": "10080737",
    "name": "田中　千佳子",
    "jobType": "補助",
    "birthDate": "1970-12-26",
    "hireDate": "2016-02-22",
    "baseSalary": 194000,
    "adjustment": 30000,
    "commute": 4200,
    "baseR8": 200000,
    "adjR8": 70000,
    "position": 0,
    "positionR8": 0,
    "_i": 76,
    "_ex": false,
    "_a7": 3270000,
    "_a8": 3840000,
    "_ur": 17.431192660550458,
    "_lsEx": false,
    "_blEx": false,
    "_blAge": 55,
    "_blSv": {
      "d": 3691,
      "r": 1
    },
    "_blBBase": 590000,
    "_blBConf": 590000,
    "_blLBase": 190000,
    "_blLConf": 190000,
    "_blTotal": 780000
  },
  {
    "id": "10080799",
    "name": "宗藤　晴美",
    "jobType": "補助",
    "birthDate": "1981-11-28",
    "hireDate": "2018-04-01",
    "baseSalary": 143000,
    "adjustment": 38000,
    "commute": 19700,
    "baseR8": 145000,
    "adjR8": 42000,
    "position": 0,
    "positionR8": 0,
    "_i": 77,
    "_ex": false,
    "_a7": 2601000,
    "_a8": 2679000,
    "_ur": 2.9988465974625145,
    "_blEx": false,
    "_blAge": 44,
    "_blSv": {
      "d": 2922,
      "r": 1
    },
    "_blBBase": 430000,
    "_blBConf": 430000,
    "_blLBase": 26000,
    "_blLConf": 49000,
    "_blTotal": 479000
  },
  {
    "id": "10080860",
    "name": "逸見　祥子",
    "jobType": "補助",
    "birthDate": "1984-11-06",
    "hireDate": "2020-03-30",
    "baseSalary": 160000,
    "adjustment": 28000,
    "commute": 13500,
    "baseR8": 160000,
    "adjR8": 36000,
    "position": 0,
    "positionR8": 0,
    "_i": 78,
    "_ex": false,
    "_a7": 2736000,
    "_a8": 2832000,
    "_ur": 3.508771929824561,
    "_blEx": false,
    "_blAge": 41,
    "_blSv": {
      "d": 2193,
      "r": 1
    },
    "_blBBase": 480000,
    "_blBConf": 480000,
    "_blLBase": 32000,
    "_blLConf": 32000,
    "_blTotal": 512000
  },
  {
    "id": "10080888",
    "name": "加藤　玉恵",
    "jobType": "補助",
    "birthDate": "1969-02-24",
    "hireDate": "2020-08-17",
    "baseSalary": 150000,
    "adjustment": 35000,
    "commute": 13500,
    "baseR8": 150000,
    "adjR8": 40000,
    "position": 0,
    "_idx": 50,
    "_excluded": false,
    "_annualSalary": 2670000,
    "_annualSalaryR8": 2730000,
    "_upRatio": 2.247191011235955,
    "_as": 2670000,
    "_asr": 2730000,
    "_ur": 2.247191011235955,
    "_i": 79,
    "_ex": false,
    "_a7": 2670000,
    "_a8": 2730000,
    "_lsEx": false,
    "_blEx": false,
    "_blAge": 57,
    "_blSv": {
      "d": 2053,
      "r": 1
    },
    "_blBBase": 450000,
    "_blBConf": 450000,
    "_blLBase": 20000,
    "_blLConf": 20000,
    "_blTotal": 470000
  },
  {
    "id": "10080941",
    "name": "上田　温奈",
    "jobType": "補助",
    "birthDate": "1987-11-29",
    "hireDate": "2022-07-11",
    "baseSalary": 157000,
    "adjustment": 40000,
    "commute": 4200,
    "baseR8": 180000,
    "adjR8": 45000,
    "position": 0,
    "positionR8": 0,
    "_i": 80,
    "_ex": false,
    "_a7": 2835000,
    "_a8": 3240000,
    "_ur": 14.285714285714285,
    "_blEx": false,
    "_blAge": 38,
    "_blSv": {
      "d": 1360,
      "r": 1
    },
    "_blBBase": 480000,
    "_blBConf": 480000,
    "_blLBase": 135000,
    "_blLConf": 160000,
    "_blTotal": 640000
  },
  {
    "id": "10080967",
    "name": "三宅　正子",
    "jobType": "補助",
    "birthDate": "1975-02-20",
    "hireDate": "2026-01-01",
    "baseSalary": 150000,
    "adjustment": 38000,
    "commute": 0,
    "baseR8": 150000,
    "adjR8": 40000,
    "position": 0,
    "_idx": 118,
    "_excluded": false,
    "_annualSalary": 2706000,
    "_annualSalaryR8": 2730000,
    "_upRatio": 0.8869179600886918,
    "_as": 2706000,
    "_asr": 2730000,
    "_ur": 0.8869179600886918,
    "_i": 81,
    "_ex": false,
    "_a7": 2706000,
    "_a8": 2730000,
    "_lsEx": false,
    "_blEx": false,
    "_blAge": 51,
    "_blSv": {
      "d": 90,
      "r": 0.2465753424657534
    },
    "_blBBase": 120000,
    "_blBConf": 120000,
    "_blLBase": 8000,
    "_blLConf": 8000,
    "_blTotal": 128000
  },
  {
    "id": "10081024",
    "name": "中井　捺貴",
    "jobType": "補助",
    "birthDate": "1997-05-01",
    "hireDate": "2025-04-01",
    "baseSalary": 143000,
    "adjustment": 38000,
    "commute": 4200,
    "baseR8": 160000,
    "adjR8": 36000,
    "position": 0,
    "positionR8": 0,
    "_i": 82,
    "_ex": false,
    "_a7": 2601000,
    "_a8": 2832000,
    "_ur": 8.881199538638986,
    "_blEx": false,
    "_blAge": 28,
    "_blSv": {
      "d": 365,
      "r": 1
    },
    "_blBBase": 430000,
    "_blBConf": 480000,
    "_blLBase": 77000,
    "_blLConf": 127000,
    "_blTotal": 607000
  },
  {
    "id": "10081041",
    "name": "伊達　弥生",
    "jobType": "補助",
    "birthDate": "1978-03-06",
    "hireDate": "2025-10-16",
    "baseSalary": 162000,
    "adjustment": 38000,
    "commute": 4200,
    "baseR8": 180000,
    "adjR8": 50000,
    "position": 0,
    "positionR8": 0,
    "_i": 83,
    "_ex": false,
    "_a7": 2886000,
    "_a8": 3300000,
    "_ur": 14.345114345114347,
    "_blEx": false,
    "_blAge": 48,
    "_blSv": {
      "d": 167,
      "r": 0.4575342465753425
    },
    "_blBBase": 230000,
    "_blBConf": 280000,
    "_blLBase": 138000,
    "_blLConf": 138000,
    "_blTotal": 418000
  },
  {
    "id": "10150730",
    "name": "八木　直希",
    "jobType": "栄養",
    "birthDate": "1984-08-27",
    "hireDate": "2015-07-01",
    "baseSalary": 230000,
    "adjustment": 40000,
    "commute": 13500,
    "baseR8": 230000,
    "adjR8": 50000,
    "position": 40000,
    "positionR8": 40000,
    "_i": 84,
    "_ex": false,
    "_a7": 4410000,
    "_a8": 4530000,
    "_ur": 2.7210884353741496,
    "_blEx": false,
    "_blAge": 41,
    "_blSv": {
      "d": 3927,
      "r": 1
    },
    "_blBBase": 690000,
    "_blBConf": 700000,
    "_blLBase": 40000,
    "_blLConf": 40000,
    "_blTotal": 740000
  },
  {
    "id": "10170587",
    "name": "藤原　典子",
    "jobType": "調理",
    "birthDate": "1988-04-04",
    "hireDate": "2009-09-01",
    "baseSalary": 150000,
    "adjustment": 75000,
    "commute": 4200,
    "baseR8": 160000,
    "adjR8": 70000,
    "position": 0,
    "_idx": 38,
    "_excluded": false,
    "_annualSalary": 3150000,
    "_annualSalaryR8": 3240000,
    "_upRatio": 2.857142857142857,
    "_as": 3150000,
    "_asr": 3240000,
    "_ur": 2.857142857142857,
    "_i": 85,
    "_ex": false,
    "_a7": 3150000,
    "_a8": 3240000,
    "_lsEx": false,
    "_blEx": false,
    "_blAge": 37,
    "_blSv": {
      "d": 6056,
      "r": 1
    },
    "_blBBase": 450000,
    "_blBConf": 450000,
    "_blLBase": 30000,
    "_blLConf": 30000,
    "_blTotal": 480000
  },
  {
    "id": "10170614",
    "name": "平田　弘美",
    "jobType": "調理",
    "birthDate": "1961-05-15",
    "hireDate": "2010-12-01",
    "baseSalary": 0,
    "adjustment": 246000,
    "commute": 0,
    "baseR8": 0,
    "adjR8": 246000,
    "position": 0,
    "_idx": 39,
    "_annualSalary": 2952000,
    "_upRatio": 0,
    "_excluded": false,
    "_annualSalaryR8": 2952000,
    "_as": 2952000,
    "_asr": 2952000,
    "_ur": 0,
    "_i": 86,
    "_ex": false,
    "_a7": 2952000,
    "_a8": 2952000,
    "_lsEx": false,
    "_blEx": false,
    "_blAge": 64,
    "_blSv": {
      "d": 5600,
      "r": 1
    },
    "_blBBase": 0,
    "_blBConf": 0,
    "_blLBase": 0,
    "_blLConf": 0,
    "_blTotal": 0
  },
  {
    "id": "10170687",
    "name": "弓取　かすみ",
    "jobType": "調理",
    "birthDate": "1979-07-06",
    "hireDate": "2014-01-01",
    "baseSalary": 180000,
    "adjustment": 57000,
    "commute": 13500,
    "baseR8": 180000,
    "adjR8": 75000,
    "position": 0,
    "positionR8": 0,
    "_i": 87,
    "_ex": false,
    "_a7": 3384000,
    "_a8": 3600000,
    "_ur": 6.382978723404255,
    "_blEx": false,
    "_blAge": 46,
    "_blSv": {
      "d": 4473,
      "r": 1
    },
    "_blBBase": 540000,
    "_blBConf": 600000,
    "_blLBase": 72000,
    "_blLConf": 72000,
    "_blTotal": 672000
  },
  {
    "id": "10170688",
    "name": "蛭子　奈々",
    "jobType": "調理",
    "birthDate": "1976-07-25",
    "hireDate": "2014-01-01",
    "baseSalary": 150000,
    "adjustment": 75000,
    "commute": 4200,
    "baseR8": 160000,
    "adjR8": 68000,
    "position": 0,
    "_idx": 41,
    "_excluded": false,
    "_annualSalary": 3150000,
    "_annualSalaryR8": 3216000,
    "_upRatio": 2.0952380952380953,
    "_as": 3150000,
    "_asr": 3216000,
    "_ur": 2.0952380952380953,
    "_i": 88,
    "_ex": false,
    "_a7": 3150000,
    "_a8": 3216000,
    "_lsEx": false,
    "_blEx": false,
    "_blAge": 49,
    "_blSv": {
      "d": 4473,
      "r": 1
    },
    "_blBBase": 450000,
    "_blBConf": 450000,
    "_blLBase": 22000,
    "_blLConf": 22000,
    "_blTotal": 472000
  },
  {
    "id": "10170765",
    "name": "瀧川　和恵",
    "jobType": "調理",
    "birthDate": "1968-07-20",
    "hireDate": "2017-02-01",
    "baseSalary": 160000,
    "adjustment": 66000,
    "commute": 13500,
    "baseR8": 160000,
    "adjR8": 75000,
    "position": 0,
    "_idx": 42,
    "_annualSalary": 3192000,
    "_upRatio": 3.3834586466165413,
    "_excluded": false,
    "_annualSalaryR8": 3300000,
    "_as": 3192000,
    "_asr": 3300000,
    "_ur": 3.3834586466165413,
    "_i": 89,
    "_ex": false,
    "_a7": 3192000,
    "_a8": 3300000,
    "_lsEx": false,
    "_blEx": false,
    "_blAge": 57,
    "_blSv": {
      "d": 3346,
      "r": 1
    },
    "_blBBase": 480000,
    "_blBConf": 480000,
    "_blLBase": 36000,
    "_blLConf": 36000,
    "_blTotal": 516000
  },
  {
    "id": "10170831",
    "name": "山川　徹",
    "jobType": "調理",
    "birthDate": "1981-12-04",
    "hireDate": "2019-04-01",
    "baseSalary": 150000,
    "adjustment": 75000,
    "commute": 7300,
    "baseR8": 160000,
    "adjR8": 72000,
    "position": 0,
    "_idx": 43,
    "_excluded": false,
    "_annualSalary": 3150000,
    "_annualSalaryR8": 3264000,
    "_upRatio": 3.619047619047619,
    "_as": 3150000,
    "_asr": 3264000,
    "_ur": 3.619047619047619,
    "_i": 90,
    "_ex": false,
    "_a7": 3150000,
    "_a8": 3264000,
    "_lsEx": false,
    "_blEx": false,
    "_blAge": 44,
    "_blSv": {
      "d": 2557,
      "r": 1
    },
    "_blBBase": 450000,
    "_blBConf": 450000,
    "_blLBase": 38000,
    "_blLConf": 38000,
    "_blTotal": 488000
  },
  {
    "id": "10170856",
    "name": "藤森　晴香",
    "jobType": "調理",
    "birthDate": "1998-11-14",
    "hireDate": "2020-02-01",
    "baseSalary": 160000,
    "adjustment": 63000,
    "commute": 13500,
    "baseR8": 160000,
    "adjR8": 75000,
    "position": 0,
    "_idx": 44,
    "_annualSalary": 3156000,
    "_upRatio": 4.562737642585551,
    "_excluded": false,
    "_annualSalaryR8": 3300000,
    "_as": 3156000,
    "_asr": 3300000,
    "_ur": 4.562737642585551,
    "_i": 91,
    "_ex": false,
    "_a7": 3156000,
    "_a8": 3300000,
    "_lsEx": false,
    "_blEx": false,
    "_blAge": 27,
    "_blSv": {
      "d": 2251,
      "r": 1
    },
    "_blBBase": 480000,
    "_blBConf": 480000,
    "_blLBase": 48000,
    "_blLConf": 60000,
    "_blTotal": 540000
  },
  {
    "id": "10170924",
    "name": "平松　誠治",
    "jobType": "調理",
    "birthDate": "1970-08-25",
    "hireDate": "2022-01-01",
    "baseSalary": 160000,
    "adjustment": 64000,
    "commute": 4200,
    "baseR8": 160000,
    "adjR8": 75000,
    "position": 0,
    "_idx": 52,
    "_excluded": false,
    "_annualSalary": 3168000,
    "_annualSalaryR8": 3300000,
    "_upRatio": 4.166666666666666,
    "_as": 3168000,
    "_asr": 3300000,
    "_ur": 4.166666666666666,
    "_i": 92,
    "_ex": false,
    "_a7": 3168000,
    "_a8": 3300000,
    "_lsEx": false,
    "_blEx": false,
    "_blAge": 55,
    "_blSv": {
      "d": 1551,
      "r": 1
    },
    "_blBBase": 480000,
    "_blBConf": 480000,
    "_blLBase": 44000,
    "_blLConf": 44000,
    "_blTotal": 524000
  },
  {
    "id": "10170928",
    "name": "秋山　太志",
    "jobType": "調理",
    "birthDate": "1997-07-25",
    "hireDate": "2022-02-01",
    "baseSalary": 145000,
    "adjustment": 76000,
    "commute": 4200,
    "baseR8": 160000,
    "adjR8": 60000,
    "position": 0,
    "_idx": 53,
    "_excluded": false,
    "_annualSalary": 3087000,
    "_annualSalaryR8": 3120000,
    "_upRatio": 1.0689990281827018,
    "_as": 3087000,
    "_asr": 3120000,
    "_ur": 1.0689990281827018,
    "_i": 93,
    "_ex": false,
    "_a7": 3087000,
    "_a8": 3120000,
    "_lsEx": false,
    "_blEx": false,
    "_blAge": 28,
    "_blSv": {
      "d": 1520,
      "r": 1
    },
    "_blBBase": 440000,
    "_blBConf": 440000,
    "_blLBase": 11000,
    "_blLConf": 11000,
    "_blTotal": 451000
  },
  {
    "id": "10170946",
    "name": "藤井　巳希",
    "jobType": "調理",
    "birthDate": "1985-09-16",
    "hireDate": "2022-09-20",
    "baseSalary": 150000,
    "adjustment": 75000,
    "commute": 0,
    "baseR8": 160000,
    "adjR8": 68000,
    "position": 0,
    "_idx": 71,
    "_excluded": false,
    "_annualSalary": 3150000,
    "_annualSalaryR8": 3216000,
    "_upRatio": 2.0952380952380953,
    "_as": 3150000,
    "_asr": 3216000,
    "_ur": 2.0952380952380953,
    "_i": 94,
    "_ex": false,
    "_a7": 3150000,
    "_a8": 3216000,
    "_lsEx": false,
    "_blEx": false,
    "_blAge": 40,
    "_blSv": {
      "d": 1289,
      "r": 1
    },
    "_blBBase": 450000,
    "_blBConf": 450000,
    "_blLBase": 22000,
    "_blLConf": 22000,
    "_blTotal": 472000
  },
  {
    "id": "10200480",
    "name": "岡　奈緒美",
    "jobType": "OT",
    "birthDate": "1983-10-28",
    "hireDate": "2006-04-01",
    "baseSalary": 258000,
    "adjustment": 59000,
    "commute": 19700,
    "baseR8": 260000,
    "adjR8": 59000,
    "position": 0,
    "positionR8": 0,
    "_i": 95,
    "_ex": false,
    "_a7": 4578000,
    "_a8": 4608000,
    "_ur": 0.655307994757536,
    "_blEx": false,
    "_blAge": 42,
    "_blSv": {
      "d": 7305,
      "r": 1
    },
    "_blBBase": 780000,
    "_blBConf": 800000,
    "_blLBase": 10000,
    "_blLConf": 10000,
    "_blTotal": 810000
  },
  {
    "id": "10200644",
    "name": "護田　隼也",
    "jobType": "OT",
    "birthDate": "1988-07-06",
    "hireDate": "2012-04-01",
    "baseSalary": 236000,
    "adjustment": 38000,
    "commute": 19700,
    "baseR8": 260000,
    "adjR8": 50000,
    "position": 20000,
    "positionR8": 0,
    "_i": 96,
    "_ex": false,
    "_a7": 4236000,
    "_a8": 4500000,
    "_ur": 6.232294617563739,
    "_blEx": false,
    "_blAge": 37,
    "_blSv": {
      "d": 5113,
      "r": 1
    },
    "_blBBase": 710000,
    "_blBConf": 750000,
    "_blLBase": 88000,
    "_blLConf": 88000,
    "_blTotal": 838000
  },
  {
    "id": "10200649",
    "name": "伊藤　和也",
    "jobType": "OT",
    "birthDate": "1985-04-13",
    "hireDate": "2012-07-01",
    "baseSalary": 239000,
    "adjustment": 40000,
    "commute": 19700,
    "baseR8": 260000,
    "adjR8": 50000,
    "position": 40000,
    "positionR8": 40000,
    "_i": 97,
    "_ex": false,
    "_a7": 4545000,
    "_a8": 4980000,
    "_ur": 9.570957095709572,
    "_blEx": false,
    "_blAge": 40,
    "_blSv": {
      "d": 5022,
      "r": 1
    },
    "_blBBase": 720000,
    "_blBConf": 800000,
    "_blLBase": 145000,
    "_blLConf": 145000,
    "_blTotal": 945000
  },
  {
    "id": "10200667",
    "name": "江草　香織",
    "jobType": "OT",
    "birthDate": "1983-08-29",
    "hireDate": "2013-03-01",
    "baseSalary": 246000,
    "adjustment": 38000,
    "commute": 4200,
    "baseR8": 260000,
    "adjR8": 40000,
    "position": 0,
    "positionR8": 0,
    "_i": 98,
    "_ex": false,
    "_a7": 4146000,
    "_a8": 4380000,
    "_ur": 5.643994211287988,
    "_blEx": false,
    "_blAge": 42,
    "_blSv": {
      "d": 4779,
      "r": 1
    },
    "_blBBase": 740000,
    "_blBConf": 750000,
    "_blLBase": 78000,
    "_blLConf": 78000,
    "_blTotal": 828000
  },
  {
    "id": "10200747",
    "name": "近藤　加奈子",
    "jobType": "OT",
    "birthDate": "1993-11-15",
    "hireDate": "2016-04-01",
    "baseSalary": 225000,
    "adjustment": 38000,
    "commute": 19700,
    "baseR8": 250000,
    "adjR8": 40000,
    "position": 0,
    "positionR8": 0,
    "_i": 99,
    "_ex": false,
    "_a7": 3831000,
    "_a8": 4230000,
    "_ur": 10.415035238841034,
    "_blEx": false,
    "_blAge": 32,
    "_blSv": {
      "d": 3652,
      "r": 1
    },
    "_blBBase": 680000,
    "_blBConf": 700000,
    "_blLBase": 133000,
    "_blLConf": 133000,
    "_blTotal": 833000
  },
  {
    "id": "10400442",
    "name": "坂田　大輔",
    "jobType": "事業",
    "birthDate": "1981-01-08",
    "hireDate": "2004-02-01",
    "baseSalary": 260000,
    "adjustment": 40000,
    "commute": 0,
    "baseR8": 260000,
    "adjR8": 60000,
    "position": 60000,
    "positionR8": 60000,
    "_i": 100,
    "_ex": false,
    "_a7": 5100000,
    "_a8": 5340000,
    "_ur": 4.705882352941177,
    "_blEx": false,
    "_blAge": 45,
    "_blSv": {
      "d": 8095,
      "r": 1
    },
    "_blBBase": 780000,
    "_blBConf": 1000000,
    "_blLBase": 80000,
    "_blLConf": 120000,
    "_blTotal": 1120000
  },
  {
    "id": "10400643",
    "name": "下平　耕司",
    "jobType": "事業",
    "birthDate": "1983-06-06",
    "hireDate": "2012-04-01",
    "baseSalary": 240000,
    "adjustment": 40000,
    "commute": 38700,
    "baseR8": 240000,
    "adjR8": 40000,
    "position": 40000,
    "positionR8": 40000,
    "_idx": 9,
    "_excluded": false,
    "_annualSalary": 4560000,
    "_annualSalaryR8": 4560000,
    "_upRatio": 0,
    "_as": 4560000,
    "_asr": 4560000,
    "_ur": 0,
    "_i": 101,
    "_ex": false,
    "_a7": 4560000,
    "_a8": 4560000,
    "_lsEx": false,
    "_blEx": false,
    "_blAge": 42,
    "_blSv": {
      "d": 5113,
      "r": 1
    },
    "_blBBase": 720000,
    "_blBConf": 750000,
    "_blLBase": 0,
    "_blLConf": 50000,
    "_blTotal": 800000
  },
  {
    "id": "10400796",
    "name": "宮本　陽子",
    "jobType": "事業",
    "birthDate": "1971-01-04",
    "hireDate": "2018-04-01",
    "baseSalary": 240000,
    "adjustment": 50000,
    "commute": 4200,
    "baseR8": 240000,
    "adjR8": 50000,
    "position": 40000,
    "positionR8": 40000,
    "_idx": 33,
    "_excluded": false,
    "_annualSalary": 4680000,
    "_annualSalaryR8": 4680000,
    "_upRatio": 0,
    "_as": 4680000,
    "_asr": 4680000,
    "_ur": 0,
    "_i": 102,
    "_ex": false,
    "_a7": 4680000,
    "_a8": 4680000,
    "_lsEx": false,
    "_blEx": false,
    "_blAge": 55,
    "_blSv": {
      "d": 2922,
      "r": 1
    },
    "_blBBase": 720000,
    "_blBConf": 750000,
    "_blLBase": 0,
    "_blLConf": 50000,
    "_blTotal": 800000
  },
  {
    "id": "10400807",
    "name": "松本　京子",
    "jobType": "事業",
    "birthDate": "1977-01-17",
    "hireDate": "2018-04-16",
    "baseSalary": 210000,
    "adjustment": 50000,
    "commute": 0,
    "baseR8": 210000,
    "adjR8": 62000,
    "position": 0,
    "positionR8": 0,
    "_i": 103,
    "_ex": false,
    "_a7": 3750000,
    "_a8": 3894000,
    "_ur": 3.84,
    "_lsEx": false,
    "_blEx": false,
    "_blAge": 49,
    "_blSv": {
      "d": 2907,
      "r": 1
    },
    "_blBBase": 630000,
    "_blBConf": 650000,
    "_blLBase": 48000,
    "_blLConf": 50000,
    "_blTotal": 700000
  },
  {
    "id": "10400963",
    "name": "椎名　理恵",
    "jobType": "事業",
    "birthDate": "1974-05-02",
    "hireDate": "2023-06-21",
    "baseSalary": 210000,
    "adjustment": 35000,
    "commute": 13500,
    "baseR8": 210000,
    "adjR8": 50000,
    "position": 0,
    "positionR8": 0,
    "_i": 104,
    "_ex": false,
    "_a7": 3570000,
    "_a8": 3750000,
    "_ur": 5.042016806722689,
    "_lsEx": false,
    "_blEx": false,
    "_blAge": 51,
    "_blSv": {
      "d": 1015,
      "r": 1
    },
    "_blBBase": 630000,
    "_blBConf": 900000,
    "_blLBase": 60000,
    "_blLConf": 60000,
    "_blTotal": 960000
  },
  {
    "id": "10400965",
    "name": "持田　志織",
    "jobType": "事業",
    "birthDate": "1984-09-26",
    "hireDate": "2023-06-21",
    "baseSalary": 220000,
    "adjustment": 45000,
    "commute": 13500,
    "baseR8": 220000,
    "adjR8": 50000,
    "position": 0,
    "positionR8": 0,
    "_i": 105,
    "_ex": false,
    "_a7": 3840000,
    "_a8": 3900000,
    "_ur": 1.5625,
    "_blEx": false,
    "_blAge": 41,
    "_blSv": {
      "d": 1015,
      "r": 1
    },
    "_blBBase": 660000,
    "_blBConf": 660000,
    "_blLBase": 20000,
    "_blLConf": 40000,
    "_blTotal": 700000
  },
  {
    "id": "40160085",
    "name": "松本　洋",
    "jobType": "支援",
    "birthDate": "1968-12-13",
    "hireDate": "1988-02-01",
    "baseSalary": 280000,
    "adjustment": 50000,
    "commute": 4200,
    "baseR8": 280000,
    "adjR8": 60000,
    "position": 40000,
    "positionR8": 40000,
    "_idx": 82,
    "_excluded": false,
    "_annualSalary": 5280000,
    "_annualSalaryR8": 5400000,
    "_upRatio": 2.272727272727273,
    "_i": 106,
    "_ex": false,
    "_a7": 5280000,
    "_a8": 5400000,
    "_ur": 2.272727272727273,
    "_lsEx": false,
    "_blEx": false,
    "_blAge": 57,
    "_blSv": {
      "d": 13939,
      "r": 1
    },
    "_blBBase": 840000,
    "_blBConf": 1000000,
    "_blLBase": 40000,
    "_blLConf": 0,
    "_blTotal": 1000000
  },
  {
    "id": "40160549",
    "name": "田村　昌三",
    "jobType": "支援",
    "birthDate": "1984-06-25",
    "hireDate": "2008-10-01",
    "baseSalary": 170000,
    "adjustment": 22000,
    "commute": 7300,
    "baseR8": 180000,
    "adjR8": 30000,
    "position": 0,
    "_idx": 68,
    "_excluded": false,
    "_annualSalary": 2814000,
    "_annualSalaryR8": 3060000,
    "_upRatio": 8.742004264392325,
    "_i": 107,
    "_ex": false,
    "_a7": 2814000,
    "_a8": 3060000,
    "_ur": 8.742004264392325,
    "_lsEx": false,
    "_blEx": false,
    "_blAge": 41,
    "_blSv": {
      "d": 6391,
      "r": 1
    },
    "_blBBase": 510000,
    "_blBConf": 480000,
    "_blLBase": 82000,
    "_blLConf": 0,
    "_blTotal": 480000
  },
  {
    "id": "40160559",
    "name": "赤木　明美",
    "jobType": "支援",
    "birthDate": "1961-08-14",
    "hireDate": "2009-02-01",
    "baseSalary": 0,
    "adjustment": 200000,
    "commute": 13500,
    "baseR8": 0,
    "adjR8": 200000,
    "position": 0,
    "_idx": 65,
    "_excluded": false,
    "_annualSalary": 2400000,
    "_annualSalaryR8": 2400000,
    "_upRatio": 0,
    "_i": 108,
    "_ex": false,
    "_a7": 2400000,
    "_a8": 2400000,
    "_ur": 0,
    "_lsEx": false,
    "_blEx": false,
    "_blAge": 64,
    "_blSv": {
      "d": 6268,
      "r": 1
    },
    "_blBBase": 0,
    "_blBConf": 0,
    "_blLBase": 0,
    "_blLConf": 0,
    "_blTotal": 0
  },
  {
    "id": "40160631",
    "name": "中村　義浩",
    "jobType": "支援",
    "birthDate": "1961-10-18",
    "hireDate": "2011-06-10",
    "baseSalary": 0,
    "adjustment": 250000,
    "commute": 4200,
    "baseR8": 0,
    "adjR8": 250000,
    "position": 0,
    "_idx": 54,
    "_excluded": false,
    "_annualSalary": 3000000,
    "_annualSalaryR8": 3000000,
    "_upRatio": 0,
    "_i": 109,
    "_ex": false,
    "_a7": 3000000,
    "_a8": 3000000,
    "_ur": 0,
    "_lsEx": false,
    "_blEx": false,
    "_blAge": 64,
    "_blSv": {
      "d": 5409,
      "r": 1
    },
    "_blBBase": 0,
    "_blBConf": 0,
    "_blLBase": 0,
    "_blLConf": 0,
    "_blTotal": 0
  },
  {
    "id": "40160660",
    "name": "荊尾　清美",
    "jobType": "支援",
    "birthDate": "1969-12-05",
    "hireDate": "2012-10-01",
    "baseSalary": 240000,
    "adjustment": 15000,
    "commute": 4200,
    "baseR8": 250000,
    "adjR8": 20000,
    "position": 60000,
    "positionR8": 60000,
    "_idx": 58,
    "_excluded": false,
    "_annualSalary": 4500000,
    "_annualSalaryR8": 4710000,
    "_upRatio": 4.666666666666667,
    "_i": 110,
    "_ex": false,
    "_a7": 4500000,
    "_a8": 4710000,
    "_ur": 4.666666666666667,
    "_lsEx": false,
    "_blEx": false,
    "_blAge": 56,
    "_blSv": {
      "d": 4930,
      "r": 1
    },
    "_blBBase": 720000,
    "_blBConf": 800000,
    "_blLBase": 70000,
    "_blLConf": 0,
    "_blTotal": 800000
  },
  {
    "id": "40160696",
    "name": "井上　裕之",
    "jobType": "支援",
    "birthDate": "1986-12-19",
    "hireDate": "2014-04-01",
    "baseSalary": 206000,
    "adjustment": 38000,
    "commute": 19700,
    "baseR8": 0,
    "adjR8": 0,
    "position": 20000,
    "positionR8": 0,
    "_idx": 55,
    "_excluded": false,
    "_annualSalary": 3786000,
    "_annualSalaryR8": 0,
    "_upRatio": -100,
    "_i": 111,
    "_ex": false,
    "_a7": 3786000,
    "_a8": 0,
    "_ur": -100,
    "_lsEx": false,
    "_blEx": false,
    "_blAge": 39,
    "_blSv": {
      "d": 4383,
      "r": 1
    },
    "_blBBase": 620000,
    "_blBConf": 620000,
    "_blLBase": -1262000,
    "_blLConf": 0,
    "_blTotal": 620000
  },
  {
    "id": "40160740",
    "name": "継山　由佳",
    "jobType": "支援",
    "birthDate": "1985-09-10",
    "hireDate": "2016-04-01",
    "baseSalary": 170000,
    "adjustment": 8000,
    "commute": 4200,
    "baseR8": 180000,
    "adjR8": 0,
    "position": 0,
    "positionR8": 0,
    "_i": 112,
    "_ex": false,
    "_a7": 2646000,
    "_a8": 2700000,
    "_ur": 2.0408163265306123,
    "_blEx": false,
    "_blAge": 40,
    "_blSv": {
      "d": 3652,
      "r": 1
    },
    "_blBBase": 510000,
    "_blBConf": 510000,
    "_blLBase": 18000,
    "_blLConf": 0,
    "_blTotal": 510000
  },
  {
    "id": "40160874",
    "name": "澤木　康晃",
    "jobType": "支援",
    "birthDate": "1969-05-27",
    "hireDate": "2020-06-11",
    "baseSalary": 170000,
    "adjustment": 38000,
    "commute": 4200,
    "baseR8": 180000,
    "adjR8": 40000,
    "position": 0,
    "_idx": 67,
    "_excluded": false,
    "_annualSalary": 3006000,
    "_annualSalaryR8": 3180000,
    "_upRatio": 5.788423153692615,
    "_i": 113,
    "_ex": false,
    "_a7": 3006000,
    "_a8": 3180000,
    "_ur": 5.788423153692615,
    "_lsEx": false,
    "_blEx": false,
    "_blAge": 56,
    "_blSv": {
      "d": 2120,
      "r": 1
    },
    "_blBBase": 510000,
    "_blBConf": 500000,
    "_blLBase": 58000,
    "_blLConf": 0,
    "_blTotal": 500000
  },
  {
    "id": "40160907",
    "name": "菅田　和真",
    "jobType": "支援",
    "birthDate": "1998-11-09",
    "hireDate": "2021-04-01",
    "baseSalary": 216000,
    "adjustment": 28000,
    "commute": 32300,
    "baseR8": 220000,
    "adjR8": 50000,
    "position": 0,
    "_idx": 78,
    "_excluded": false,
    "_annualSalary": 3576000,
    "_annualSalaryR8": 3900000,
    "_upRatio": 9.060402684563758,
    "_i": 114,
    "_ex": false,
    "_a7": 3576000,
    "_a8": 3900000,
    "_ur": 9.060402684563758,
    "_lsEx": false,
    "_blEx": false,
    "_blAge": 27,
    "_blSv": {
      "d": 1826,
      "r": 1
    },
    "_blBBase": 650000,
    "_blBConf": 700000,
    "_blLBase": 108000,
    "_blLConf": 0,
    "_blTotal": 700000
  },
  {
    "id": "40160911",
    "name": "山田　京子",
    "jobType": "支援",
    "birthDate": "1976-02-26",
    "hireDate": "2021-04-01",
    "baseSalary": 178000,
    "adjustment": 34000,
    "commute": 0,
    "baseR8": 180000,
    "adjR8": 40000,
    "position": 0,
    "_idx": 59,
    "_excluded": false,
    "_annualSalary": 3078000,
    "_annualSalaryR8": 3180000,
    "_upRatio": 3.313840155945419,
    "_i": 115,
    "_ex": false,
    "_a7": 3078000,
    "_a8": 3180000,
    "_ur": 3.313840155945419,
    "_lsEx": false,
    "_blEx": false,
    "_blAge": 50,
    "_blSv": {
      "d": 1826,
      "r": 1
    },
    "_blBBase": 540000,
    "_blBConf": 540000,
    "_blLBase": 34000,
    "_blLConf": 0,
    "_blTotal": 540000
  },
  {
    "id": "40160912",
    "name": "立森　純子",
    "jobType": "支援",
    "birthDate": "1972-02-19",
    "hireDate": "2021-04-21",
    "baseSalary": 170000,
    "adjustment": 8000,
    "commute": 0,
    "baseR8": 180000,
    "adjR8": 30000,
    "position": 0,
    "positionR8": 0,
    "_i": 116,
    "_ex": false,
    "_a7": 2646000,
    "_a8": 3060000,
    "_ur": 15.646258503401361,
    "_blEx": false,
    "_blAge": 54,
    "_blSv": {
      "d": 1806,
      "r": 1
    },
    "_blBBase": 510000,
    "_blBConf": 510000,
    "_blLBase": 138000,
    "_blLConf": 0,
    "_blTotal": 510000
  },
  {
    "id": "40160916",
    "name": "南　譲",
    "jobType": "支援",
    "birthDate": "1990-12-03",
    "hireDate": "2024-08-21",
    "baseSalary": 170000,
    "adjustment": 8000,
    "commute": 19700,
    "baseR8": 180000,
    "adjR8": 0,
    "position": 0,
    "positionR8": 0,
    "_i": 117,
    "_ex": false,
    "_a7": 2646000,
    "_a8": 2700000,
    "_ur": 2.0408163265306123,
    "_blEx": false,
    "_blAge": 35,
    "_blSv": {
      "d": 588,
      "r": 1
    },
    "_blBBase": 510000,
    "_blBConf": 400000,
    "_blLBase": 18000,
    "_blLConf": 0,
    "_blTotal": 400000
  },
  {
    "id": "40300594",
    "name": "栁井　康延",
    "jobType": "支援",
    "birthDate": "1968-12-26",
    "hireDate": "2009-11-16",
    "baseSalary": 176000,
    "adjustment": 38000,
    "commute": 4200,
    "baseR8": 180000,
    "adjR8": 60000,
    "position": 20000,
    "positionR8": 0,
    "_i": 118,
    "_ex": false,
    "_a7": 3336000,
    "_a8": 3420000,
    "_ur": 2.5179856115107913
  },
  {
    "id": "40300679",
    "name": "赤埴　誠",
    "jobType": "支援",
    "birthDate": "1962-08-24",
    "hireDate": "2013-05-01",
    "baseSalary": 0,
    "adjustment": 250000,
    "commute": 7300,
    "baseR8": 0,
    "adjR8": 250000,
    "position": 0,
    "_idx": 56,
    "_excluded": false,
    "_annualSalary": 3000000,
    "_annualSalaryR8": 3000000,
    "_upRatio": 0,
    "_i": 119,
    "_ex": false,
    "_a7": 3000000,
    "_a8": 3000000,
    "_ur": 0,
    "_lsEx": false,
    "_blEx": false,
    "_blAge": 63,
    "_blSv": {
      "d": 4718,
      "r": 1
    },
    "_blBBase": 0,
    "_blBConf": 0,
    "_blLBase": 0,
    "_blLConf": 0,
    "_blTotal": 0
  },
  {
    "id": "40300759",
    "name": "大倉　寛充",
    "jobType": "支援",
    "birthDate": "1971-10-20",
    "hireDate": "2016-10-01",
    "baseSalary": 170000,
    "adjustment": 38000,
    "commute": 19700,
    "baseR8": 180000,
    "adjR8": 40000,
    "position": 0,
    "positionR8": 0,
    "_i": 120,
    "_ex": false,
    "_a7": 3006000,
    "_a8": 3180000,
    "_ur": 5.788423153692615,
    "_lsEx": false,
    "_blEx": false,
    "_blAge": 54,
    "_blSv": {
      "d": 3469,
      "r": 1
    },
    "_blBBase": 510000,
    "_blBConf": 460000,
    "_blLBase": 58000,
    "_blLConf": 0,
    "_blTotal": 460000
  },
  {
    "id": "40300773",
    "name": "山本　浩司",
    "jobType": "支援",
    "birthDate": "1986-11-29",
    "hireDate": "2017-04-01",
    "baseSalary": 228000,
    "adjustment": 66000,
    "commute": 19700,
    "baseR8": 230000,
    "adjR8": 70000,
    "position": 0,
    "_idx": 77,
    "_excluded": false,
    "_annualSalary": 4212000,
    "_annualSalaryR8": 4290000,
    "_upRatio": 1.8518518518518516,
    "_i": 121,
    "_ex": false,
    "_a7": 4212000,
    "_a8": 4290000,
    "_ur": 1.8518518518518516,
    "_lsEx": false,
    "_blEx": false,
    "_blAge": 39,
    "_blSv": {
      "d": 3287,
      "r": 1
    },
    "_blBBase": 690000,
    "_blBConf": 780000,
    "_blLBase": 26000,
    "_blLConf": 0,
    "_blTotal": 780000
  },
  {
    "id": "40300894",
    "name": "大石　丈司",
    "jobType": "支援",
    "birthDate": "1974-01-18",
    "hireDate": "2021-01-01",
    "baseSalary": 160000,
    "adjustment": 32000,
    "commute": 13500,
    "baseR8": 0,
    "adjR8": 0,
    "position": 0,
    "positionR8": 0,
    "_i": 122,
    "_ex": false,
    "_a7": 2784000,
    "_a8": 0,
    "_ur": -100,
    "_lsEx": false,
    "_blEx": false,
    "_blAge": 52,
    "_blSv": {
      "d": 1916,
      "r": 1
    },
    "_blBBase": 480000,
    "_blBConf": 480000,
    "_blLBase": -928000,
    "_blLConf": 0,
    "_blTotal": 480000
  },
  {
    "id": "40300954",
    "name": "水本　卓司",
    "jobType": "支援",
    "birthDate": "1968-07-08",
    "hireDate": "2023-03-21",
    "baseSalary": 170000,
    "adjustment": 8000,
    "commute": 7300,
    "baseR8": 180000,
    "adjR8": 30000,
    "position": 0,
    "_idx": 73,
    "_excluded": false,
    "_annualSalary": 2646000,
    "_annualSalaryR8": 3060000,
    "_upRatio": 15.646258503401361,
    "_i": 123,
    "_ex": false,
    "_a7": 2646000,
    "_a8": 3060000,
    "_ur": 15.646258503401361,
    "_lsEx": false,
    "_blEx": false,
    "_blAge": 57,
    "_blSv": {
      "d": 1107,
      "r": 1
    },
    "_blBBase": 510000,
    "_blBConf": 510000,
    "_blLBase": 138000,
    "_blLConf": 0,
    "_blTotal": 510000
  },
  {
    "id": "40301054",
    "name": "野見　吉江",
    "jobType": "支援",
    "birthDate": "1977-10-31",
    "hireDate": "2026-02-01",
    "baseSalary": 170000,
    "adjustment": 38000,
    "commute": 13500,
    "baseR8": 170000,
    "adjR8": 38000,
    "position": 0,
    "_idx": 120,
    "_excluded": false,
    "_annualSalary": 3006000,
    "_annualSalaryR8": 3006000,
    "_upRatio": 0,
    "_i": 124,
    "_ex": false,
    "_a7": 3006000,
    "_a8": 3006000,
    "_ur": 0,
    "_lsEx": false,
    "_blEx": false,
    "_blAge": 48,
    "_blSv": {
      "d": 59,
      "r": 0.16164383561643836
    },
    "_blBBase": 90000,
    "_blBConf": 0,
    "_blLBase": 0,
    "_blLConf": 0,
    "_blTotal": 0
  },
  {
    "id": "40350915",
    "name": "河原　真恵",
    "jobType": "支援",
    "birthDate": "1979-01-23",
    "hireDate": "2021-06-01",
    "baseSalary": 186000,
    "adjustment": 57000,
    "commute": 0,
    "baseR8": 190000,
    "adjR8": 60000,
    "position": 0,
    "_idx": 60,
    "_excluded": false,
    "_annualSalary": 3474000,
    "_annualSalaryR8": 3570000,
    "_upRatio": 2.763385146804836,
    "_i": 125,
    "_ex": false,
    "_a7": 3474000,
    "_a8": 3570000,
    "_ur": 2.763385146804836,
    "_lsEx": false,
    "_blEx": false,
    "_blAge": 47,
    "_blSv": {
      "d": 1765,
      "r": 1
    },
    "_blBBase": 560000,
    "_blBConf": 560000,
    "_blLBase": 32000,
    "_blLConf": 0,
    "_blTotal": 560000
  }
]